[
 {
  "document_id": "008de59a-5a7b-4813-ab10-e08769ccc08a",
  "product_id": "010XM001",
  "brand": "Xtreme X Martial Arts",
  "name": "Snakebloom Unisex Joggers",
  "price": "999",
  "image_urls": "https:\/\/xtremexmartialarts.com\/wp-content\/uploads\/2025\/01\/jogger-5-510x611.jpg, https:\/\/xtremexmartialarts.com\/wp-content\/uploads\/2025\/01\/1L9A1303-510x765.jpg, https:\/\/xtremexmartialarts.com\/wp-content\/uploads\/2025\/01\/1L9A1286-510x765.jpg",
  "url": "https:\/\/xtremexmartialarts.com\/product\/snakebloom-unisex-joggers\/",
  "material": "Polyester",
  "exported_at": "2026-01-02 22:18:18",
  "article": "Men's Apparel",
  "timestamp": "2025-06-15 19:37:27",
  "category": "Men's Apparel",
  "platform": "Xtreme X Martial Arts"
 },
 {
  "document_id": "035ef910-ec7f-43b4-8ac9-c7c4fcf170bc",
  "product_id": "010XM002",
  "brand": "Xtreme X Martial Arts",
  "name": "Dagger Unisex Joggers",
  "price": "999",
  "image_urls": "https:\/\/xtremexmartialarts.com\/wp-content\/uploads\/2025\/02\/new-jogger-2-510x611.jpg, https:\/\/xtremexmartialarts.com\/wp-content\/uploads\/2025\/02\/1L9A1257-510x765.jpg, https:\/\/xtremexmartialarts.com\/wp-content\/uploads\/2025\/02\/1L9A1259-510x765.jpg",
  "url": "https:\/\/xtremexmartialarts.com\/product\/dagger-unisex-joggers\/",
  "material": "Polyester",
  "exported_at": "2026-01-02 22:18:18",
  "article": "Men's Apparel",
  "timestamp": "2025-06-15 19:37:27",
  "category": "Men's Apparel",
  "platform": "Xtreme X Martial Arts"
 },
 {
  "document_id": "072f2e1b-6342-42d3-bbfc-ce9cada736a4",
  "product_id": "010XM003",
  "brand": "Xtreme X Martial Arts",
  "name": "Spider Compression 2.0 Tshirt Half Sleeve",
  "price": "899",
  "image_urls": "https:\/\/xtremexmartialarts.com\/cdn\/shop\/files\/IMG_0685-1.png?v=1754021938&width=1944",
  "url": "https:\/\/xtremexmartialarts.com\/product\/spider-compression-2-0-tshirt-half-sleeve\/",
  "material": "Polyester",
  "exported_at": "2026-01-02 22:18:18",
  "article": "Men's Apparel",
  "timestamp": "2025-06-15 19:37:27",
  "category": "Men's Apparel",
  "platform": "Xtreme X Martial Arts"
 },
 {
  "document_id": "084ce16a-ec82-4971-a1c6-bfc2f4443cb7",
  "product_id": "010XM004",
  "brand": "Xtreme X Martial Arts",
  "name": "hunderStrike Unisex Oversized Tshirt",
  "price": "899",
  "image_urls": "https:\/\/xtremexmartialarts.com\/wp-content\/uploads\/2025\/01\/jogger-11-510x611.jpg, https:\/\/xtremexmartialarts.com\/wp-content\/uploads\/2025\/01\/1L9A1181-510x765.jpg, https:\/\/xtremexmartialarts.com\/wp-content\/uploads\/2025\/01\/1L9A1176-510x765.jpg",
  "url": "https:\/\/xtremexmartialarts.com\/product\/thunderstrike-unisex-oversized-tshirt\/",
  "material": "Polyester",
  "exported_at": "2026-01-02 22:18:18",
  "article": "Men's Apparel",
  "timestamp": "2025-06-15 19:37:27",
  "category": "Men's Apparel",
  "platform": "Xtreme X Martial Arts"
 },
 {
  "document_id": "09b798db-ceb7-4e8b-a44c-5e2944e0c77e",
  "product_id": "010XM005",
  "brand": "Xtreme X Martial Arts",
  "name": "Dominance Unisex Oversized Tshirt",
  "price": "899",
  "image_urls": "https:\/\/xtremexmartialarts.com\/wp-content\/uploads\/2025\/01\/jogger-8-510x611.jpg, https:\/\/xtremexmartialarts.com\/wp-content\/uploads\/2025\/01\/1L9A1235-510x765.jpg, https:\/\/xtremexmartialarts.com\/wp-content\/uploads\/2025\/01\/1L9A1239-510x765.jpg",
  "url": "https:\/\/xtremexmartialarts.com\/product\/dominance-unisex-oversized-tshirt\/",
  "material": "Polyester",
  "exported_at": "2026-01-02 22:18:18",
  "article": "Men's Apparel",
  "timestamp": "2025-06-15 19:37:27",
  "category": "Men's Apparel",
  "platform": "Xtreme X Martial Arts"
 },
 {
  "document_id": "0N4kIdNLteyDkqmRY5Fc",
  "product_id": "010GE001",
  "brand": "Genrage",
  "name": "MUTATION UNISEX STRAIGHT FIT BAGGY PANTS",
  "price": "1799.00",
  "image_urls": "https:\/\/genrage.com\/cdn\/shop\/files\/70.png?v=1742290581&width=1000",
  "url": "https:\/\/genrage.com\/products\/mutation-unisex-straight-fit-baggy-pants",
  "exported_at": "2026-01-02 22:18:18",
  "article": "Men's Gym Wear",
  "timestamp": "2025-05-29 18:39:05",
  "platform": "Genrage"
 },
 {
  "document_id": "0affa79d-3e82-408d-922e-07ee44add558",
  "product_id": "010XM006",
  "brand": "Xtreme X Martial Arts",
  "name": "Nightchain Unisex Joggers",
  "price": "1199",
  "image_urls": "https:\/\/xtremexmartialarts.com\/wp-content\/uploads\/2024\/12\/image00013-510x611.png, https:\/\/xtremexmartialarts.com\/wp-content\/uploads\/2024\/12\/image00011-510x510.png, https:\/\/xtremexmartialarts.com\/wp-content\/uploads\/2024\/12\/image00012-510x510.png",
  "url": "https:\/\/xtremexmartialarts.com\/product\/nightchain-unisex-joggers\/",
  "material": "Polyester",
  "exported_at": "2026-01-02 22:18:18",
  "article": "Men's Apparel",
  "timestamp": "2025-06-15 19:37:27",
  "category": "Men's Apparel",
  "platform": "Xtreme X Martial Arts"
 },
 {
  "document_id": "0eb05591-d457-4385-bfa3-7e3f9d445df7",
  "product_id": "010XM007",
  "brand": "Xtreme X Martial Arts",
  "name": "Evil Inside Unisex Oversized Tshirt",
  "price": "999",
  "image_urls": "https:\/\/xtremexmartialarts.com\/wp-content\/uploads\/2025\/04\/t-shirts-n-1-510x611.jpg, https:\/\/xtremexmartialarts.com\/wp-content\/uploads\/2025\/04\/front-view-hanging-t-shirt-mockup-white-tee-against-deep-red-wall-clean-and-eye-catching-presentation-0995-22-510x638.jpg, https:\/\/xtremexmartialarts.com\/wp-content\/uploads\/2025\/04\/back-view-hanging-t-shirt-mockup-white-tee-on-vibrant-red-wall-minimalist-display-bold-and-modern-aesthetic1-0994-23-510x638.jpg",
  "url": "https:\/\/xtremexmartialarts.com\/product\/evil-inside-unisex-oversized-tshirt\/",
  "material": "Polyester",
  "exported_at": "2026-01-02 22:18:18",
  "article": "Men's Apparel",
  "timestamp": "2025-06-15 18:41:08",
  "category": "Men's Apparel",
  "platform": "Xtreme X Martial Arts"
 },
 {
  "document_id": "10b0a32d-be35-423f-af8f-e836044820d4",
  "product_id": "010XM008",
  "brand": "Xtreme X Martial Arts",
  "name": "Stringline Unisex Joggers",
  "price": "999",
  "image_urls": "https:\/\/xtremexmartialarts.com\/wp-content\/uploads\/2024\/12\/image00025-510x611.png, https:\/\/xtremexmartialarts.com\/wp-content\/uploads\/2024\/12\/image00026-510x510.png, https:\/\/xtremexmartialarts.com\/wp-content\/uploads\/2024\/12\/image00027-510x510.png",
  "url": "https:\/\/xtremexmartialarts.com\/product\/stringline-unisex-joggers\/",
  "material": "Polyester",
  "exported_at": "2026-01-02 22:18:18",
  "article": "Men's Apparel",
  "timestamp": "2025-06-15 19:37:27",
  "category": "Men's Apparel",
  "platform": "Xtreme X Martial Arts"
 },
 {
  "document_id": "1173e529-3401-4069-ae72-ce5008eeff89",
  "product_id": "010XM009",
  "brand": "Xtreme X Martial Arts",
  "name": "NYC Unisex Joggers",
  "price": "999",
  "image_urls": "https:\/\/xtremexmartialarts.com\/wp-content\/uploads\/2025\/01\/jogger-4-510x611.jpg, https:\/\/xtremexmartialarts.com\/wp-content\/uploads\/2025\/01\/1L9A1316-510x765.jpg, https:\/\/xtremexmartialarts.com\/wp-content\/uploads\/2025\/01\/1L9A1308-510x765.jpg",
  "url": "https:\/\/xtremexmartialarts.com\/product\/nyc-unisex-joggers\/?attribute_pa_color=teal",
  "material": "Polyester",
  "exported_at": "2026-01-02 22:18:18",
  "article": "Men's Apparel",
  "timestamp": "2025-06-15 19:37:27",
  "category": "Men's Apparel",
  "platform": "Xtreme X Martial Arts"
 },
 {
  "document_id": "12afdb36-174e-43c2-ac0a-de21aa5ff2ef",
  "product_id": "010XM010",
  "brand": "Xtreme X Martial Arts",
  "name": "InkRose Unisex Joggers",
  "price": "999",
  "image_urls": "https:\/\/xtremexmartialarts.com\/wp-content\/uploads\/2025\/06\/JOGGER--510x611.jpg, https:\/\/xtremexmartialarts.com\/wp-content\/uploads\/2025\/06\/21.1w-510x306.png, https:\/\/xtremexmartialarts.com\/wp-content\/uploads\/2025\/06\/21.3-510x510.png",
  "url": "https:\/\/xtremexmartialarts.com\/product\/inkrose-unisex-joggers\/",
  "material": "Polyester",
  "exported_at": "2026-01-02 22:18:18",
  "article": "Men's Apparel",
  "timestamp": "2025-06-15 18:41:08",
  "category": "Men's Apparel",
  "platform": "Xtreme X Martial Arts"
 },
 {
  "document_id": "13178b2f-8b92-4858-a70a-92b8889ee51d",
  "product_id": "010XM011",
  "brand": "Xtreme X Martial Arts",
  "name": "King Unisex Oversized Tshirt",
  "price": "899",
  "image_urls": "https:\/\/xtremexmartialarts.com\/wp-content\/uploads\/2025\/01\/jogger-14-510x611.jpg, https:\/\/xtremexmartialarts.com\/wp-content\/uploads\/2025\/01\/1L9A1138-510x765.jpg, https:\/\/xtremexmartialarts.com\/wp-content\/uploads\/2025\/01\/1L9A1140-510x765.jpg",
  "url": "https:\/\/xtremexmartialarts.com\/product\/king-unisex-oversized-tshirt\/",
  "material": "Polyester",
  "exported_at": "2026-01-02 22:18:18",
  "article": "Men's Apparel",
  "timestamp": "2025-06-15 19:37:27",
  "category": "Men's Apparel",
  "platform": "Xtreme X Martial Arts"
 },
 {
  "document_id": "17aa6b52-36d0-4369-8eb4-e309a891bab5",
  "product_id": "010XM012",
  "brand": "Xtreme X Martial Arts",
  "name": "Alpha Compression Tshirt Full Sleeve",
  "price": "1199",
  "image_urls": "https:\/\/xtremexmartialarts.com\/cdn\/shop\/files\/T-SHIRTS-14.jpg?v=1754023255&width=1946",
  "url": "https:\/\/xtremexmartialarts.com\/product\/alpha-compression-tshirt-full-sleeve\/?attribute_pa_color=apple-green",
  "material": "Polyester",
  "exported_at": "2026-01-02 22:18:18",
  "article": "Men's Apparel",
  "timestamp": "2025-06-15 19:37:27",
  "category": "Men's Apparel",
  "platform": "Xtreme X Martial Arts"
 },
 {
  "document_id": "1f9c6987-9b07-480c-bf87-af4f61b87f9a",
  "product_id": "010XM013",
  "brand": "Xtreme X Martial Arts",
  "name": "Super Suit Compression Tshirt Full Sleeve",
  "price": "949",
  "image_urls": "https:\/\/xtremexmartialarts.com\/cdn\/shop\/files\/T-SHIRTS-46.jpg?v=1754023146&width=1944",
  "url": "https:\/\/xtremexmartialarts.com\/product\/super-suit-compression-tshirt-full-sleeve\/",
  "material": "Polyester",
  "exported_at": "2026-01-02 22:18:18",
  "article": "Men's Apparel",
  "timestamp": "2025-06-15 19:37:27",
  "category": "Men's Apparel",
  "platform": "Xtreme X Martial Arts"
 },
 {
  "document_id": "2087ad02-7503-4622-81d8-5c4a0fbc35a2",
  "product_id": "010XM014",
  "brand": "Xtreme X Martial Arts",
  "name": "NYC Unisex Joggers",
  "price": "999",
  "image_urls": "https:\/\/xtremexmartialarts.com\/wp-content\/uploads\/2025\/01\/jogger-18-510x611.jpg, https:\/\/xtremexmartialarts.com\/wp-content\/uploads\/2025\/01\/1L9A1070-510x765.jpg, https:\/\/xtremexmartialarts.com\/wp-content\/uploads\/2025\/01\/1L9A1067-510x765.jpg",
  "url": "https:\/\/xtremexmartialarts.com\/product\/nyc-unisex-joggers\/?attribute_pa_color=red",
  "material": "Polyester",
  "exported_at": "2026-01-02 22:18:18",
  "article": "Men's Apparel",
  "timestamp": "2025-06-15 19:37:27",
  "category": "Men's Apparel",
  "platform": "Xtreme X Martial Arts"
 },
 {
  "document_id": "34Tf5dk0lyPxW1pgZeIn",
  "product_id": "010GE002",
  "brand": "Genrage",
  "name": "VAMP BLACK UNISEX BOXY VEST",
  "price": "999.00",
  "image_urls": "https:\/\/genrage.com\/cdn\/shop\/files\/26_84d80b39-d278-458d-9121-886ec179efad.png?v=1741373308&width=1000",
  "url": "https:\/\/genrage.com\/products\/vamp-black-unisex-boxy-vest",
  "exported_at": "2026-01-02 22:18:18",
  "article": "Men's Gym Wear",
  "timestamp": "2025-05-29 19:10:21",
  "platform": "Genrage"
 },
 {
  "document_id": "363427b2-0f75-4055-80c9-f51b1ebf3d08",
  "product_id": "010XM015",
  "brand": "Xtreme X Martial Arts",
  "name": "Beast Unisex Oversized Tshir",
  "price": "899",
  "image_urls": "https:\/\/xtremexmartialarts.com\/wp-content\/uploads\/2025\/01\/jogger-9-510x611.jpg, https:\/\/xtremexmartialarts.com\/wp-content\/uploads\/2025\/01\/1L9A1217-510x765.jpg, https:\/\/xtremexmartialarts.com\/wp-content\/uploads\/2025\/01\/1L9A1208-510x765.jpg",
  "url": "https:\/\/xtremexmartialarts.com\/product\/beast-unisex-oversized-tshirt\/",
  "material": "Polyester",
  "exported_at": "2026-01-02 22:18:18",
  "article": "Men's Apparel",
  "timestamp": "2025-06-15 19:37:27",
  "category": "Men's Apparel",
  "platform": "Xtreme X Martial Arts"
 },
 {
  "document_id": "39dd83d1-c335-45be-90df-69d035578526",
  "product_id": "010XM016",
  "brand": "Xtreme X Martial Arts",
  "name": "Aquawave Unisex Joggers",
  "price": "1199",
  "image_urls": "https:\/\/xtremexmartialarts.com\/wp-content\/uploads\/2024\/12\/image00002-1-510x611.png, https:\/\/xtremexmartialarts.com\/wp-content\/uploads\/2024\/12\/image00002-1.png, https:\/\/xtremexmartialarts.com\/wp-content\/uploads\/2024\/12\/image00001-510x510.png",
  "url": "https:\/\/xtremexmartialarts.com\/product\/aquawave-unisex-joggers\/",
  "material": "Polyester",
  "exported_at": "2026-01-02 22:18:18",
  "article": "Men's Apparel",
  "timestamp": "2025-06-15 19:37:27",
  "category": "Men's Apparel",
  "platform": "Xtreme X Martial Arts"
 },
 {
  "document_id": "3ec32749-b95b-414d-8533-8f21960e9f99",
  "product_id": "010XM017",
  "brand": "Xtreme X Martial Arts",
  "name": "Savage Compression Tshirt Full Sleeve",
  "price": "949",
  "image_urls": "https:\/\/xtremexmartialarts.com\/cdn\/shop\/files\/IMG_1075-1.png?v=1754022318&width=1944",
  "url": "https:\/\/xtremexmartialarts.com\/product\/savage-compression-tshirt-full-sleeve\/",
  "material": "Polyester",
  "exported_at": "2026-01-02 22:18:18",
  "article": "Men's Apparel",
  "timestamp": "2025-06-15 19:37:27",
  "category": "Men's Apparel",
  "platform": "Xtreme X Martial Arts"
 },
 {
  "document_id": "41010fdc-b6ba-479a-a81c-085d21bce53d",
  "product_id": "010XM018",
  "brand": "Xtreme X Martial Arts",
  "name": "ColourDrip Unisex Joggers",
  "price": "999",
  "image_urls": "https:\/\/xtremexmartialarts.com\/wp-content\/uploads\/2025\/06\/JOGGER-2-510x611.jpg, https:\/\/xtremexmartialarts.com\/wp-content\/uploads\/2025\/06\/23.1y-510x510.png, https:\/\/xtremexmartialarts.com\/wp-content\/uploads\/2025\/06\/23.2-510x510.png",
  "url": "https:\/\/xtremexmartialarts.com\/product\/colourdrip-unisex-joggers\/",
  "material": "Polyester",
  "exported_at": "2026-01-02 22:18:18",
  "article": "Men's Apparel",
  "timestamp": "2025-06-15 18:41:08",
  "category": "Men's Apparel",
  "platform": "Xtreme X Martial Arts"
 },
 {
  "document_id": "4670df59-efa5-4686-a126-223c71934ec3",
  "product_id": "010XM019",
  "brand": "Xtreme X Martial Arts",
  "name": "Tribal Compression Tshirt Full Sleeve",
  "price": "949",
  "image_urls": "https:\/\/xtremexmartialarts.com\/cdn\/shop\/files\/T-SHIRTS-22.jpg?v=1754023201&width=1944",
  "url": "https:\/\/xtremexmartialarts.com\/product\/tribal-compression-tshirt-full-sleeve\/?attribute_pa_color=white",
  "material": "Polyester",
  "exported_at": "2026-01-02 22:18:18",
  "article": "Men's Apparel",
  "timestamp": "2025-06-15 19:37:27",
  "category": "Men's Apparel",
  "platform": "Xtreme X Martial Arts"
 },
 {
  "document_id": "46d0c44d-26ea-475b-a048-ac2f6a36d5fe",
  "product_id": "010XM020",
  "brand": "Xtreme X Martial Arts",
  "name": "Alpha Compression Tshirt Full Sleeve",
  "price": "1199",
  "image_urls": "https:\/\/xtremexmartialarts.com\/cdn\/shop\/files\/T-SHIRTS-14.jpg?v=1754023255&width=1944",
  "url": "https:\/\/xtremexmartialarts.com\/product\/alpha-compression-tshirt-full-sleeve\/?attribute_pa_color=ice-blue",
  "material": "Polyester",
  "exported_at": "2026-01-02 22:18:18",
  "article": "Men's Apparel",
  "timestamp": "2025-06-15 19:37:27",
  "category": "Men's Apparel",
  "platform": "Xtreme X Martial Arts"
 },
 {
  "document_id": "46ec474f-4daa-4d67-b408-3ef5cb6dfdc1",
  "product_id": "010XM021",
  "brand": "Xtreme X Martial Arts",
  "name": "Venom Compression Tshirt 2.0 Full Sleeve",
  "price": "949",
  "image_urls": "https:\/\/xtremexmartialarts.com\/cdn\/shop\/files\/IMG_1077.png?v=1754022286&width=1944",
  "url": "https:\/\/xtremexmartialarts.com\/product\/venom-compression-tshirt-2-0-full-sleeve\/",
  "material": "Polyester",
  "exported_at": "2026-01-02 22:18:18",
  "article": "Men's Apparel",
  "timestamp": "2025-06-15 19:37:27",
  "category": "Men's Apparel",
  "platform": "Xtreme X Martial Arts"
 },
 {
  "document_id": "4a96eece-d3ae-495d-ae9b-dc44e71f7dfb",
  "product_id": "010XM022",
  "brand": "Xtreme X Martial Arts",
  "name": "Savage Compression Tshirt Half Sleeve",
  "price": "899",
  "image_urls": "https:\/\/xtremexmartialarts.com\/cdn\/shop\/files\/IMG_1076-1.png?v=1754022303&width=1944",
  "url": "https:\/\/xtremexmartialarts.com\/product\/savage-compression-tshirt-half-sleeve\/",
  "material": "Polyester",
  "exported_at": "2026-01-02 22:18:18",
  "article": "Men's Apparel",
  "timestamp": "2025-06-15 19:37:27",
  "category": "Men's Apparel",
  "platform": "Xtreme X Martial Arts"
 },
 {
  "document_id": "4c3d1283-4658-48b3-aaa5-a43599147d59",
  "product_id": "010XM023",
  "brand": "Xtreme X Martial Arts",
  "name": "Wildcat Unisex Joggers",
  "price": "999",
  "image_urls": "https:\/\/xtremexmartialarts.com\/wp-content\/uploads\/2024\/11\/IMG_0508-510x611.png, https:\/\/xtremexmartialarts.com\/wp-content\/uploads\/2024\/11\/2.1-510x510.png",
  "url": "https:\/\/xtremexmartialarts.com\/product\/wildcat-unisex-joggers\/",
  "material": "Polyester",
  "exported_at": "2026-01-02 22:18:18",
  "article": "Men's Apparel",
  "timestamp": "2025-06-15 19:37:27",
  "category": "Men's Apparel",
  "platform": "Xtreme X Martial Arts"
 },
 {
  "document_id": "4d0c73ed-99c2-4d30-b758-6207a0f6cbc0",
  "product_id": "010XM024",
  "brand": "Xtreme X Martial Arts",
  "name": "Night Web Compression Tshirt Half Sleeve",
  "price": "899",
  "image_urls": "https:\/\/xtremexmartialarts.com\/cdn\/shop\/files\/image00005-2.png?v=1754022914&width=1944",
  "url": "https:\/\/xtremexmartialarts.com\/product\/night-web-compression-tshirt-half-sleeve\/",
  "material": "Polyester",
  "exported_at": "2026-01-02 22:18:18",
  "article": "Men's Apparel",
  "timestamp": "2025-06-15 19:37:27",
  "category": "Men's Apparel",
  "platform": "Xtreme X Martial Arts"
 },
 {
  "document_id": "51f25a43-0d87-42c3-a678-1879644e033e",
  "product_id": "010XM025",
  "brand": "Xtreme X Martial Arts",
  "name": "Firestrike Unisex Joggers",
  "price": "999",
  "image_urls": "https:\/\/xtremexmartialarts.com\/wp-content\/uploads\/2025\/01\/new-jogger-1-510x611.jpg, https:\/\/xtremexmartialarts.com\/wp-content\/uploads\/2025\/01\/1L9A1193-510x765.jpg",
  "url": "https:\/\/xtremexmartialarts.com\/product\/firestrike-unisex-joggers\/",
  "material": "Polyester",
  "exported_at": "2026-01-02 22:18:18",
  "article": "Men's Apparel",
  "timestamp": "2025-06-15 19:37:27",
  "category": "Men's Apparel",
  "platform": "Xtreme X Martial Arts"
 },
 {
  "document_id": "58d7de61-b5bc-4a9d-a2ae-75d153796af3",
  "product_id": "010XM026",
  "brand": "Xtreme X Martial Arts",
  "name": "Flame Wings Unisex Oversized Tshirt",
  "price": "999",
  "image_urls": "https:\/\/xtremexmartialarts.com\/wp-content\/uploads\/2025\/04\/t-shirts-n-2-510x611.jpg, https:\/\/xtremexmartialarts.com\/wp-content\/uploads\/2025\/04\/front-view-hanging-t-shirt-mockup-white-tee-against-deep-red-wall-clean-and-eye-catching-presentation-0995-21-510x638.jpg",
  "url": "https:\/\/xtremexmartialarts.com\/product\/flame-wings-unisex-oversized-tshirt\/",
  "material": "Polyester",
  "exported_at": "2026-01-02 22:18:18",
  "article": "Men's Apparel",
  "timestamp": "2025-06-15 18:41:08",
  "category": "Men's Apparel",
  "platform": "Xtreme X Martial Arts"
 },
 {
  "document_id": "5T8WuhlrS3gvpJiuzHWB",
  "product_id": "010GE003",
  "brand": "Genrage",
  "name": "TOJI UNISEX STRAIGHT FIT BAGGY PANTS",
  "price": "1699.00",
  "image_urls": "https:\/\/genrage.com\/cdn\/shop\/files\/38_1.png?v=1743699725&width=1000",
  "url": "https:\/\/genrage.com\/products\/toji-unisex-straight-fit-baggy-pants",
  "exported_at": "2026-01-02 22:18:18",
  "article": "Men's Gym Wear",
  "timestamp": "2025-05-29 18:37:54",
  "platform": "Genrage"
 },
 {
  "document_id": "5c1b7d95-a377-448b-bea0-48ae4775e0f0",
  "product_id": "010XM027",
  "brand": "Xtreme X Martial Arts",
  "name": "Divine Unisex Oversized Tshirt",
  "price": "899",
  "image_urls": "https:\/\/xtremexmartialarts.com\/wp-content\/uploads\/2025\/02\/minimalist-studio-t-shirt-mockup-floating-display-with-sunlit-effect-and-subtle-textures-596-8-1-510x611.jpg.webp, https:\/\/xtremexmartialarts.com\/wp-content\/uploads\/2025\/02\/folded-white-tshirt-mockup-on-wooden-surface-0390-1-510x408.jpg.webp",
  "url": "https:\/\/xtremexmartialarts.com\/product\/divine-unisex-oversized-tshirt\/",
  "material": "Polyester",
  "exported_at": "2026-01-02 22:18:18",
  "article": "Men's Apparel",
  "timestamp": "2025-06-15 19:37:27",
  "category": "Men's Apparel",
  "platform": "Xtreme X Martial Arts"
 },
 {
  "document_id": "5c591000-8b5f-4a7a-b60a-31144dbd8bda",
  "product_id": "010XM028",
  "brand": "Xtreme X Martial Arts",
  "name": "Lost Soul Unisex Joggers",
  "price": "999",
  "image_urls": "https:\/\/xtremexmartialarts.com\/wp-content\/uploads\/2025\/01\/jogger-15-510x611.jpg, https:\/\/xtremexmartialarts.com\/wp-content\/uploads\/2025\/01\/1L9A1128-510x765.jpg, https:\/\/xtremexmartialarts.com\/wp-content\/uploads\/2025\/01\/1L9A1124-510x765.jpg",
  "url": "https:\/\/xtremexmartialarts.com\/product\/lost-soul-unisex-joggers\/",
  "material": "Polyester",
  "exported_at": "2026-01-02 22:18:18",
  "article": "Men's Apparel",
  "timestamp": "2025-06-15 19:37:27",
  "category": "Men's Apparel",
  "platform": "Xtreme X Martial Arts"
 },
 {
  "document_id": "5cfec044-059b-4e69-ad85-e73c2258f39a",
  "product_id": "010XM029",
  "brand": "Xtreme X Martial Arts",
  "name": "Vision Unisex Oversized Tshirt",
  "price": "899",
  "image_urls": "https:\/\/xtremexmartialarts.com\/wp-content\/uploads\/2025\/01\/jogger-19-510x611.jpg, https:\/\/xtremexmartialarts.com\/wp-content\/uploads\/2025\/01\/1L9A1051-510x765.jpg",
  "url": "https:\/\/xtremexmartialarts.com\/product\/vision-unisex-oversized-tshirt\/",
  "material": "Polyester",
  "exported_at": "2026-01-02 22:18:18",
  "article": "Men's Apparel",
  "timestamp": "2025-06-15 19:37:27",
  "category": "Men's Apparel",
  "platform": "Xtreme X Martial Arts"
 },
 {
  "document_id": "5d1a98c4-e9f4-4f72-bf4f-16a77c940de0",
  "product_id": "010XM030",
  "brand": "Xtreme X Martial Arts",
  "name": "Bolt Unisex Joggers",
  "price": "999",
  "image_urls": "https:\/\/xtremexmartialarts.com\/wp-content\/uploads\/2024\/12\/IMG_1072-1-510x611.png, https:\/\/xtremexmartialarts.com\/wp-content\/uploads\/2024\/11\/IMG_1074-510x510.png, https:\/\/xtremexmartialarts.com\/wp-content\/uploads\/2024\/11\/IMG_1073-510x510.png",
  "url": "https:\/\/xtremexmartialarts.com\/product\/bolt-unisex-joggers\/?attribute_pa_color=blue",
  "material": "Polyester",
  "exported_at": "2026-01-02 22:18:18",
  "article": "Men's Apparel",
  "timestamp": "2025-06-15 19:37:27",
  "category": "Men's Apparel",
  "platform": "Xtreme X Martial Arts"
 },
 {
  "document_id": "634de4e2-ffae-4d0f-b0c8-31b32621e4a1",
  "product_id": "010XM031",
  "brand": "Xtreme X Martial Arts",
  "name": "Blacknova Compression Tshirt Half Sleeve",
  "price": "1199",
  "image_urls": "https:\/\/xtremexmartialarts.com\/cdn\/shop\/files\/T-SHIRTS-9.jpg?v=1754023278&width=1946",
  "url": "https:\/\/xtremexmartialarts.com\/product\/blacknova-compression-tshirt-half-sleeve\/?attribute_pa_color=black-purple",
  "material": "Polyester",
  "exported_at": "2026-01-02 22:18:18",
  "article": "Men's Apparel",
  "timestamp": "2025-06-15 19:37:27",
  "category": "Men's Apparel",
  "platform": "Xtreme X Martial Arts"
 },
 {
  "document_id": "66dc3102-78e3-469b-a2c3-a32dce478256",
  "product_id": "010XM032",
  "brand": "Xtreme X Martial Arts",
  "name": "Smokeblast Unisex Joggers",
  "price": "1199",
  "image_urls": "https:\/\/xtremexmartialarts.com\/wp-content\/uploads\/2024\/12\/image00024-510x611.png, https:\/\/xtremexmartialarts.com\/wp-content\/uploads\/2024\/12\/image00015-510x510.png, https:\/\/xtremexmartialarts.com\/wp-content\/uploads\/2024\/12\/image00022-510x510.png",
  "url": "https:\/\/xtremexmartialarts.com\/product\/smokeblast-unisex-joggers\/",
  "material": "Polyester",
  "exported_at": "2026-01-02 22:18:18",
  "article": "Men's Apparel",
  "timestamp": "2025-06-15 19:37:27",
  "category": "Men's Apparel",
  "platform": "Xtreme X Martial Arts"
 },
 {
  "document_id": "6cb95992-14d6-4956-9555-58c42db1b4d1",
  "product_id": "010XM033",
  "brand": "Xtreme X Martial Arts",
  "name": "Tribal Compression Tshirt Half Sleeve",
  "price": "899",
  "image_urls": "https:\/\/xtremexmartialarts.com\/cdn\/shop\/files\/T-SHIRTS-18.jpg?v=1754023182&width=1944",
  "url": "https:\/\/xtremexmartialarts.com\/product\/tribal-compression-tshirt-half-sleeve\/?attribute_pa_color=black",
  "material": "Polyester",
  "exported_at": "2026-01-02 22:18:18",
  "article": "Men's Apparel",
  "timestamp": "2025-06-15 19:37:27",
  "category": "Men's Apparel",
  "platform": "Xtreme X Martial Arts"
 },
 {
  "document_id": "7099f486-ae46-4f60-a936-b939ce482098",
  "product_id": "010XM034",
  "brand": "Xtreme X Martial Arts",
  "name": "Vengeance Unisex Joggers",
  "price": "999",
  "image_urls": "https:\/\/xtremexmartialarts.com\/wp-content\/uploads\/2024\/12\/image00030-510x611.png, https:\/\/xtremexmartialarts.com\/wp-content\/uploads\/2024\/12\/image00029-510x510.png, https:\/\/xtremexmartialarts.com\/wp-content\/uploads\/2024\/12\/image00028-510x510.png",
  "url": "https:\/\/xtremexmartialarts.com\/product\/vengeance-unisex-joggers\/",
  "material": "Polyester",
  "exported_at": "2026-01-02 22:18:18",
  "article": "Men's Apparel",
  "timestamp": "2025-06-15 19:37:27",
  "category": "Men's Apparel",
  "platform": "Xtreme X Martial Arts"
 },
 {
  "document_id": "71zKUYL8EQWKV2CVOM2V",
  "product_id": "010GE004",
  "brand": "Genrage",
  "name": "VEDHA BLACK UNISEX STRAIGHT BAGGY PANTS",
  "price": "1699.00",
  "image_urls": "https:\/\/genrage.com\/cdn\/shop\/files\/13_3.png?v=1737608158&width=1000",
  "url": "https:\/\/genrage.com\/products\/vedha-black-unisex-straight-baggy-pants",
  "exported_at": "2026-01-02 22:18:18",
  "article": "Men's Gym Wear",
  "timestamp": "2025-05-29 18:59:14",
  "platform": "Genrage"
 },
 {
  "document_id": "73631695-d96e-4a20-8437-71930751b00f",
  "product_id": "010XM035",
  "brand": "Xtreme X Martial Arts",
  "name": "IronClawX Compression Zipper",
  "price": "1199",
  "image_urls": "https:\/\/xtremexmartialarts.com\/cdn\/shop\/files\/T-SHIRTS-16.jpg?v=1754023581&width=1944",
  "url": "https:\/\/xtremexmartialarts.com\/product\/ironclawx-compression-zipper\/",
  "material": "Polyester",
  "exported_at": "2026-01-02 22:18:18",
  "article": "Men's Apparel",
  "timestamp": "2025-06-15 18:41:08",
  "category": "Men's Apparel",
  "platform": "Xtreme X Martial Arts"
 },
 {
  "document_id": "7940522f-e0f7-4cff-b811-efdd64872e45",
  "product_id": "010XM036",
  "brand": "Xtreme X Martial Arts",
  "name": "Fear God Unisex Oversized Tshirt",
  "price": "999",
  "image_urls": "https:\/\/xtremexmartialarts.com\/wp-content\/uploads\/2025\/04\/T-SHIRTS-NEW-ONE-510x611.jpg, https:\/\/xtremexmartialarts.com\/wp-content\/uploads\/2025\/04\/front-view-hanging-t-shirt-mockup-white-tee-against-deep-red-wall-clean-and-eye-catching-presentation-0995-18-510x638.jpg",
  "url": "https:\/\/xtremexmartialarts.com\/product\/fear-god-unisex-oversized-tshirt\/",
  "material": "Polyester",
  "exported_at": "2026-01-02 22:18:18",
  "article": "Men's Apparel",
  "timestamp": "2025-06-15 18:41:08",
  "category": "Men's Apparel",
  "platform": "Xtreme X Martial Arts"
 },
 {
  "document_id": "7TUfJFPsM0KjAby8v9XK",
  "product_id": "010GE005",
  "brand": "Genrage",
  "name": "WHITE DAWN UNISEX STRAIGHT FIT BAGGY PANTS",
  "price": "1699.00",
  "image_urls": "https:\/\/genrage.com\/cdn\/shop\/files\/white_dawn.png?v=1748421931&width=1000",
  "url": "https:\/\/genrage.com\/products\/white-dawn-unisex-straight-fit-baggy-pants",
  "exported_at": "2026-01-02 22:18:18",
  "article": "Men's Gym Wear",
  "timestamp": "2025-05-29 19:04:59",
  "platform": "Genrage"
 },
 {
  "document_id": "7ab30a28-f8d8-4c76-818f-dfdd47c79a55",
  "product_id": "010XM037",
  "brand": "Xtreme X Martial Arts",
  "name": "Venom Compression Tshirt 2.0 Half Sleeve",
  "price": "899",
  "image_urls": "https:\/\/xtremexmartialarts.com\/cdn\/shop\/files\/IMG_1114.png?v=1754022270&width=1944",
  "url": "https:\/\/xtremexmartialarts.com\/product\/venom-compression-tshirt-2-0-half-sleeve\/",
  "material": "Polyester",
  "exported_at": "2026-01-02 22:18:18",
  "article": "Men's Apparel",
  "timestamp": "2025-06-15 19:37:27",
  "category": "Men's Apparel",
  "platform": "Xtreme X Martial Arts"
 },
 {
  "document_id": "7afb7932-7e84-43b6-96fc-6c792295d83f",
  "product_id": "010XM038",
  "brand": "Xtreme X Martial Arts",
  "name": "MetalX Unisex Joggers",
  "price": "999",
  "image_urls": "https:\/\/xtremexmartialarts.com\/wp-content\/uploads\/2025\/06\/JOGGER-3-510x611.jpg, https:\/\/xtremexmartialarts.com\/wp-content\/uploads\/2025\/06\/22.1f-510x465.png, https:\/\/xtremexmartialarts.com\/wp-content\/uploads\/2025\/06\/22.3-510x510.png",
  "url": "https:\/\/xtremexmartialarts.com\/product\/metalx-unisex-joggers\/",
  "material": "Polyester",
  "exported_at": "2026-01-02 22:18:18",
  "article": "Men's Apparel",
  "timestamp": "2025-06-15 18:41:08",
  "category": "Men's Apparel",
  "platform": "Xtreme X Martial Arts"
 },
 {
  "document_id": "7pEVAft7T3j4afBgnEof",
  "product_id": "010GE006",
  "brand": "Genrage",
  "name": "DEMON CORAL UNISEX BOXY VEST",
  "price": "999.00",
  "image_urls": "https:\/\/genrage.com\/cdn\/shop\/files\/32_ba089e89-650a-4649-8a6d-7d0a5f73ef3a.png?v=1743050683&width=1000",
  "url": "https:\/\/genrage.com\/products\/demon-coral-unisex-boxy-vest",
  "exported_at": "2026-01-02 22:18:18",
  "article": "Men's Gym Wear",
  "timestamp": "2025-05-29 19:06:07",
  "platform": "Genrage"
 },
 {
  "document_id": "845ebaf7-d1cf-4711-916e-43675c5ab17f",
  "product_id": "010XM039",
  "brand": "Xtreme X Martial Arts",
  "name": "Fightclub Unisex Oversized Tshirt",
  "price": "899",
  "image_urls": "https:\/\/xtremexmartialarts.com\/wp-content\/uploads\/2025\/01\/jogger-17-510x611.jpg, https:\/\/xtremexmartialarts.com\/wp-content\/uploads\/2025\/01\/1L9A1093-510x765.jpg, https:\/\/xtremexmartialarts.com\/wp-content\/uploads\/2025\/01\/1L9A1092-510x765.jpg",
  "url": "https:\/\/xtremexmartialarts.com\/product\/fightclub-unisex-oversized-tshirt\/",
  "material": "Polyester",
  "exported_at": "2026-01-02 22:18:18",
  "article": "Men's Apparel",
  "timestamp": "2025-06-15 19:37:27",
  "category": "Men's Apparel",
  "platform": "Xtreme X Martial Arts"
 },
 {
  "document_id": "862d2dc1-978a-4d86-9eff-7b8855b78bd0",
  "product_id": "010XM040",
  "brand": "Xtreme X Martial Arts",
  "name": "Cloudlight Black Unisex Joggers",
  "price": "999",
  "image_urls": "https:\/\/xtremexmartialarts.com\/wp-content\/uploads\/2025\/01\/jogger-20-510x611.jpg, https:\/\/xtremexmartialarts.com\/wp-content\/uploads\/2025\/02\/1L9A1035-510x765.jpg, https:\/\/xtremexmartialarts.com\/wp-content\/uploads\/2025\/02\/1L9A1033-510x765.jpg",
  "url": "https:\/\/xtremexmartialarts.com\/product\/cloudlight-black-unisex-joggers\/",
  "material": "Polyester",
  "exported_at": "2026-01-02 22:18:18",
  "article": "Men's Apparel",
  "timestamp": "2025-06-15 19:37:27",
  "category": "Men's Apparel",
  "platform": "Xtreme X Martial Arts"
 },
 {
  "document_id": "883e6790-f780-4afe-bc72-c0c3000c2832",
  "product_id": "010XM041",
  "brand": "Xtreme X Martial Arts",
  "name": "Blacknova Compression Tshirt Full Sleeve",
  "price": "1199",
  "image_urls": "https:\/\/xtremexmartialarts.com\/cdn\/shop\/files\/T-SHIRTS-6.jpg?v=1754023296&width=1946",
  "url": "https:\/\/xtremexmartialarts.com\/product\/blacknova-compression-tshirt-full-sleeve\/?attribute_pa_color=black-blue",
  "material": "Polyester",
  "exported_at": "2026-01-02 22:18:18",
  "article": "Men's Apparel",
  "timestamp": "2025-06-15 19:37:27",
  "category": "Men's Apparel",
  "platform": "Xtreme X Martial Arts"
 },
 {
  "document_id": "8HPEW0GfY89xELqMRyES",
  "product_id": "010GE007",
  "brand": "Genrage",
  "name": "NEXUS CHARCOAL GREY UNISEX STRAIGHT BAGGY PANTS",
  "price": "1699.00",
  "image_urls": "https:\/\/genrage.com\/cdn\/shop\/files\/69.png?v=1745485167&width=1000",
  "url": "https:\/\/genrage.com\/products\/nexus-charcoal-grey-unisex-straight-baggy-pants",
  "exported_at": "2026-01-02 22:18:18",
  "article": "Men's Gym Wear",
  "timestamp": "2025-05-29 19:02:29",
  "platform": "Genrage"
 },
 {
  "document_id": "8M5WF6Zm9KVORut1FUfG",
  "product_id": "010GE008",
  "brand": "Genrage",
  "name": "NEXUS CHARCOAL GREY UNISEX STRAIGHT BAGGY PANTS",
  "price": "1699.00",
  "image_urls": "https:\/\/genrage.com\/cdn\/shop\/files\/black_nexys.png?v=1736340485&width=1000",
  "url": "https:\/\/genrage.com\/products\/nexus-charcoal-grey-unisex-straight-baggy-pants",
  "exported_at": "2026-01-02 22:18:18",
  "article": "Men's Gym Wear",
  "timestamp": "2025-05-29 19:01:47",
  "platform": "Genrage"
 },
 {
  "document_id": "8Wr3dt1SizRHctwrF3E9",
  "product_id": "010GE009",
  "brand": "Genrage",
  "name": "1,699.00",
  "price": "1699.00",
  "image_urls": "https:\/\/genrage.com\/cdn\/shop\/files\/38_1.png?v=1743699725&width=1000",
  "url": "https:\/\/genrage.com\/products\/toji-unisex-straight-fit-baggy-pants",
  "exported_at": "2026-01-02 22:18:18",
  "article": "Men's Gym Wear",
  "timestamp": "2025-05-29 18:16:17",
  "platform": "Genrage"
 },
 {
  "document_id": "9398842c-7c12-4ee1-9548-f1879b2c6b95",
  "product_id": "010XM042",
  "brand": "Xtreme X Martial Arts",
  "name": "Spider Compression 2.0 Tshirt Full Sleeve",
  "price": "949",
  "image_urls": "https:\/\/xtremexmartialarts.com\/cdn\/shop\/files\/IMG_0687-1.png?v=1754021962&width=1944",
  "url": "https:\/\/xtremexmartialarts.com\/product\/spider-compression-2-0-tshirt-full-sleeve\/",
  "material": "Polyester",
  "exported_at": "2026-01-02 22:18:18",
  "article": "Men's Apparel",
  "timestamp": "2025-06-15 19:37:27",
  "category": "Men's Apparel",
  "platform": "Xtreme X Martial Arts"
 },
 {
  "document_id": "93dd0303-e4e6-4518-941e-f4f00a3342af",
  "product_id": "010XM043",
  "brand": "Xtreme X Martial Arts",
  "name": "Hydro Flames Unisex Joggers",
  "price": "999",
  "image_urls": "https:\/\/xtremexmartialarts.com\/wp-content\/uploads\/2025\/02\/new-jogger-3-510x611.jpg, https:\/\/xtremexmartialarts.com\/wp-content\/uploads\/2025\/02\/1L9A1284-510x765.jpg, https:\/\/xtremexmartialarts.com\/wp-content\/uploads\/2025\/02\/1L9A1276-510x765.jpg",
  "url": "https:\/\/xtremexmartialarts.com\/product\/hydro-flames-unisex-joggers\/",
  "material": "Polyester",
  "exported_at": "2026-01-02 22:18:18",
  "article": "Men's Apparel",
  "timestamp": "2025-06-15 19:37:27",
  "category": "Men's Apparel",
  "platform": "Xtreme X Martial Arts"
 },
 {
  "document_id": "96hxyB27Fv1s1aHK909M",
  "product_id": "010GE010",
  "brand": "Genrage",
  "name": "KNIGHT UNISEX BOXY VEST",
  "price": "999.00",
  "image_urls": "https:\/\/genrage.com\/cdn\/shop\/files\/68.png?v=1735063218&width=1000",
  "url": "https:\/\/genrage.com\/products\/knight-unisex-boxy-vest",
  "exported_at": "2026-01-02 22:18:18",
  "article": "Men's Gym Wear",
  "timestamp": "2025-05-29 19:09:31",
  "platform": "Genrage"
 },
 {
  "document_id": "974841a1-bada-407a-941e-8331326dfb19",
  "product_id": "010XM044",
  "brand": "Xtreme X Martial Arts",
  "name": "Panther Arc Unisex Joggers",
  "price": "999",
  "image_urls": "https:\/\/xtremexmartialarts.com\/wp-content\/uploads\/2024\/12\/image00014-510x611.png, https:\/\/xtremexmartialarts.com\/wp-content\/uploads\/2024\/12\/image00010-510x510.png, https:\/\/xtremexmartialarts.com\/wp-content\/uploads\/2024\/12\/image00016-510x510.png",
  "url": "https:\/\/xtremexmartialarts.com\/product\/panther-arc-unisex-joggers\/",
  "material": "Polyester",
  "exported_at": "2026-01-02 22:18:18",
  "article": "Men's Apparel",
  "timestamp": "2025-06-15 19:37:27",
  "category": "Men's Apparel",
  "platform": "Xtreme X Martial Arts"
 },
 {
  "document_id": "98b47fad-b138-4ca3-b39b-bdb9da8d2c23",
  "product_id": "010XM045",
  "brand": "Xtreme X Martial Arts",
  "name": "SkullSmoke Unisex Oversized Tshirt",
  "price": "899",
  "image_urls": "https:\/\/xtremexmartialarts.com\/wp-content\/uploads\/2025\/02\/minimalist-studio-t-shirt-mockup-floating-display-with-sunlit-effect-and-subtle-textures-596-2-1-510x611.jpg.webp, https:\/\/xtremexmartialarts.com\/wp-content\/uploads\/2025\/02\/blinkstore-man-tshirt-mockup-0085-7-1-510x611.jpg.webp",
  "url": "https:\/\/xtremexmartialarts.com\/product\/skullsmoke-unisex-oversized-tshirt\/",
  "material": "Polyester",
  "exported_at": "2026-01-02 22:18:18",
  "article": "Men's Apparel",
  "timestamp": "2025-06-15 19:37:27",
  "category": "Men's Apparel",
  "platform": "Xtreme X Martial Arts"
 },
 {
  "document_id": "999a919e-7e41-4e54-af51-92c8b6d90c3c",
  "product_id": "010XM046",
  "brand": "Xtreme X Martial Arts",
  "name": "Bolt Rise Unisex Oversized Tshirt",
  "price": "999",
  "image_urls": "https:\/\/xtremexmartialarts.com\/wp-content\/uploads\/2025\/04\/t-2-510x611.jpg, https:\/\/xtremexmartialarts.com\/wp-content\/uploads\/2025\/04\/front-view-hanging-t-shirt-mockup-white-tee-against-deep-red-wall-clean-and-eye-catching-presentation-0995-24-510x638.jpg, https:\/\/xtremexmartialarts.com\/wp-content\/uploads\/2025\/04\/back-view-hanging-t-shirt-mockup-white-tee-on-vibrant-red-wall-minimalist-display-bold-and-modern-aesthetic1-0994-24-510x638.jpg",
  "url": "https:\/\/xtremexmartialarts.com\/product\/bolt-rise-unisex-oversized-tshirt\/",
  "material": "Polyester",
  "exported_at": "2026-01-02 22:18:18",
  "article": "Men's Apparel",
  "timestamp": "2025-06-15 18:41:08",
  "category": "Men's Apparel",
  "platform": "Xtreme X Martial Arts"
 },
 {
  "document_id": "9E0XuBo8eLbuFXsv2hZO",
  "product_id": "010GE011",
  "brand": "Genrage",
  "name": "TOJI UNISEX STRAIGHT FIT BAGGY PANTS",
  "price": "1699.00",
  "image_urls": "https:\/\/genrage.com\/cdn\/shop\/files\/38_1.png?v=1743699725&width=1000",
  "url": "https:\/\/genrage.com\/products\/toji-unisex-straight-fit-baggy-pants",
  "exported_at": "2026-01-02 22:18:18",
  "article": "Men's Gym Wear",
  "timestamp": "2025-05-29 18:20:33",
  "platform": "Genrage"
 },
 {
  "document_id": "9OuDGSKbszkBNGHZY6Fj",
  "product_id": "010GE012",
  "brand": "Genrage",
  "name": "TEXT ME UNISEX BOXY VEST",
  "price": "999.00",
  "image_urls": "https:\/\/genrage.com\/cdn\/shop\/files\/4_1.png?v=1741373205&width=1000",
  "url": "https:\/\/genrage.com\/products\/text-me-unisex-boxy-vest",
  "exported_at": "2026-01-02 22:18:18",
  "article": "Men's Gym Wear",
  "timestamp": "2025-05-29 19:10:33",
  "platform": "Genrage"
 },
 {
  "document_id": "9bIqvRJYsGLOuHX0Wk0r",
  "product_id": "010GE013",
  "brand": "Genrage",
  "name": "Punk Coral Unisex Boxy Vest",
  "price": "999.00",
  "image_urls": "https:\/\/genrage.com\/cdn\/shop\/files\/78.png?v=1746427015&width=1000",
  "url": "https:\/\/genrage.com\/products\/punk-coral-unisex-boxy-vest",
  "exported_at": "2026-01-02 22:18:18",
  "article": "Men's Gym Wear",
  "timestamp": "2025-05-29 19:11:51",
  "platform": "Genrage"
 },
 {
  "document_id": "9d0c2b59-72be-4199-94ba-e55372f63a53",
  "product_id": "010XM047",
  "brand": "Xtreme X Martial Arts",
  "name": "mmortal Unisex Oversized Tshirt",
  "price": "999",
  "image_urls": "https:\/\/xtremexmartialarts.com\/wp-content\/uploads\/2025\/06\/hr-510x611.jpg, https:\/\/xtremexmartialarts.com\/wp-content\/uploads\/2025\/06\/back-view-hanging-t-shirt-mockup-white-tee-on-vibrant-red-wall-minimalist-display-bold-and-modern-aesthetic1-0994-29-1-510x638.jpg, https:\/\/xtremexmartialarts.com\/wp-content\/uploads\/2025\/06\/shirt-mockup-back-view-male-model-in-loose-fit-style-with-dynamic-pose-01748-510x638.jpg",
  "url": "https:\/\/xtremexmartialarts.com\/product\/immortal-unisex-oversized-tshirt\/",
  "material": "Polyester",
  "exported_at": "2026-01-02 22:18:18",
  "article": "Men's Apparel",
  "timestamp": "2025-06-15 18:41:08",
  "category": "Men's Apparel",
  "platform": "Xtreme X Martial Arts"
 },
 {
  "document_id": "9lhxsDjGe3jULwMTgFhG",
  "product_id": "010GE014",
  "brand": "Genrage",
  "name": "BEXOR BLACK UNISEX STRAIGHT FIT BAGGY PANTS",
  "price": "1699.00",
  "image_urls": "https:\/\/genrage.com\/cdn\/shop\/files\/19_1_8f260647-e920-48e3-8b87-c6b395d06143.png?v=1742290657&width=1000",
  "url": "https:\/\/genrage.com\/products\/bexor-black-unisex-straight-fit-baggy-pants",
  "exported_at": "2026-01-02 22:18:18",
  "article": "Men's Gym Wear",
  "timestamp": "2025-05-29 18:59:50",
  "platform": "Genrage"
 },
 {
  "document_id": "CNl63x7nm9liWH7BZDp0",
  "product_id": "010GE015",
  "brand": "Genrage",
  "name": "SCAR CHARCOAL GREY UNISEX STRAIGHT BAGGY PANTS",
  "price": "1699.00",
  "image_urls": "https:\/\/genrage.com\/cdn\/shop\/files\/71_136f0465-791e-4b4c-b73b-8ade6f5943ba.png?v=1745485123&width=1000",
  "url": "https:\/\/genrage.com\/products\/scar-charcoal-grey-unisex-straight-baggy-pants",
  "exported_at": "2026-01-02 22:18:18",
  "article": "Men's Gym Wear",
  "timestamp": "2025-05-29 19:00:26",
  "platform": "Genrage"
 },
 {
  "document_id": "CjUWn9IK8SG6br3bCK2b",
  "product_id": "010GE016",
  "brand": "Genrage",
  "name": "RAUDRA UNISEX STRAIGHT FIT BAGGY PANTS",
  "price": "1699.00",
  "image_urls": "https:\/\/genrage.com\/cdn\/shop\/files\/9_2.png?v=1734410701&width=1000",
  "url": "https:\/\/genrage.com\/products\/raudra-unisex-straight-fit-baggy-pants",
  "exported_at": "2026-01-02 22:18:18",
  "article": "Men's Gym Wear",
  "timestamp": "2025-05-29 18:57:06",
  "platform": "Genrage"
 },
 {
  "document_id": "D80Jr85qaFAMuZZ1Qbs3",
  "product_id": "010GE017",
  "brand": "Genrage",
  "name": "MAYA BLACK UNISEX STRAIGHT FIT BAGGY PANTS",
  "price": "1699.00",
  "image_urls": "https:\/\/genrage.com\/cdn\/shop\/files\/PNG_3_de76c6d7-4162-4b0e-8dbe-afc3a734d96e.png?v=1734410538&width=1000",
  "url": "https:\/\/genrage.com\/products\/maya-black-unisex-straight-fit-baggy-pants",
  "exported_at": "2026-01-02 22:18:18",
  "article": "Men's Gym Wear",
  "timestamp": "2025-05-29 19:04:27",
  "platform": "Genrage"
 },
 {
  "document_id": "E0w26zhww6ABVxqvMuGU",
  "product_id": "010GE018",
  "brand": "Genrage",
  "name": "BEXOR BLACK UNISEX STRAIGHT FIT BAGGY PANTS",
  "price": "1699.00",
  "image_urls": "https:\/\/genrage.com\/cdn\/shop\/files\/19_1_8f260647-e920-48e3-8b87-c6b395d06143.png?v=1742290657&width=1000",
  "url": "https:\/\/genrage.com\/products\/bexor-black-unisex-straight-fit-baggy-pants",
  "exported_at": "2026-01-02 22:18:18",
  "article": "Men's Gym Wear",
  "timestamp": "2025-05-29 19:00:46",
  "platform": "Genrage"
 },
 {
  "document_id": "EMrvQSVroy3u7jXlrVED",
  "product_id": "010GE019",
  "brand": "Genrage",
  "name": "HEAT UNISEX STRAIGHT FIT BAGGY PANTS",
  "price": "1699.00",
  "image_urls": "https:\/\/genrage.com\/cdn\/shop\/files\/ufhyjfc.png?v=1734410655&width=1000",
  "url": "https:\/\/genrage.com\/products\/heat-unisex-straight-fit-baggy-pants",
  "exported_at": "2026-01-02 22:18:18",
  "article": "Men's Gym Wear",
  "timestamp": "2025-05-29 19:04:09",
  "platform": "Genrage"
 },
 {
  "document_id": "H2ziSkmBuIF24PuSoUUs",
  "product_id": "010GE020",
  "brand": "Genrage",
  "name": "KSHAMA UNISEX BLACK BOXY VEST",
  "price": "999.00",
  "image_urls": "https:\/\/genrage.com\/cdn\/shop\/files\/1_6_ce40602e-6146-433f-8575-d0626b64cdf7.png?v=1734410735&width=1000",
  "url": "https:\/\/genrage.com\/products\/kshama-unisex-black-boxy-vest",
  "exported_at": "2026-01-02 22:18:18",
  "article": "Men's Gym Wear",
  "timestamp": "2025-05-29 19:05:32",
  "platform": "Genrage"
 },
 {
  "document_id": "HvGrK6ZP6J3XbORcwmEV",
  "product_id": "010GE021",
  "brand": "Genrage",
  "name": "Toji Unisex Straight Fit Baggy Pants",
  "price": "1699.00",
  "image_urls": "https:\/\/genrage.com\/cdn\/shop\/files\/38_1.png?v=1743699725&width=1000, na, na",
  "url": "https:\/\/genrage.com\/products\/toji-unisex-straight-fit-baggy-pants",
  "exported_at": "2026-01-02 22:18:18",
  "article": "Men's Gym Wear",
  "timestamp": "2025-05-29 18:11:20",
  "platform": "Genrage"
 },
 {
  "document_id": "Iuqk3LpNjyKSkuAO16bH",
  "product_id": "010GE022",
  "brand": "Genrage",
  "name": "STELLAR BLACK UNISEX BOXY VEST",
  "price": "999.00",
  "image_urls": "https:\/\/genrage.com\/cdn\/shop\/files\/2_60a59114-f5b4-4aed-9605-8f5803a4909b.png?v=1745296314&width=1000",
  "url": "https:\/\/genrage.com\/products\/stellar-unisex-boxy-vest",
  "exported_at": "2026-01-02 22:18:18",
  "article": "Men's Gym Wear",
  "timestamp": "2025-05-29 19:10:06",
  "platform": "Genrage"
 },
 {
  "document_id": "JG5v0UgvAYz6PqEXwSJy",
  "product_id": "010GE023",
  "brand": "Genrage",
  "name": "Apex Red Unisex Boxy Vest",
  "price": "999.00",
  "image_urls": "https:\/\/genrage.com\/cdn\/shop\/files\/Apex.png?v=1734410885&width=1000",
  "url": "https:\/\/genrage.com\/products\/apex-red-boxy-vest",
  "exported_at": "2026-01-02 22:18:18",
  "article": "Men's Gym Wear",
  "timestamp": "2025-05-29 19:07:18",
  "platform": "Genrage"
 },
 {
  "document_id": "JMjxZK5dIrQajdfffjAO",
  "product_id": "010GE024",
  "brand": "Genrage",
  "name": "DAWN UNISEX STRAIGHT FIT BAGGY PAN",
  "price": "1699.00",
  "image_urls": "https:\/\/genrage.com\/cdn\/shop\/files\/11_c39d8515-5256-4b1a-8a67-5e48a95aaa15.png?v=1739876395&width=1000",
  "url": "https:\/\/genrage.com\/products\/dawn-unisex-straight-fit-baggy-pants",
  "exported_at": "2026-01-02 22:18:18",
  "article": "Men's Gym Wear",
  "timestamp": "2025-05-29 18:57:43",
  "platform": "Genrage"
 },
 {
  "document_id": "KwO7tnnqxnDzzIj0Hjdm",
  "product_id": "010GE025",
  "brand": "Genrage",
  "name": "NOVA BLACK UNISEX STRAIGHT FIT BAGGY PANTS",
  "price": "1799.00",
  "image_urls": "https:\/\/genrage.com\/cdn\/shop\/files\/1_10.png?v=1734410860&width=1000",
  "url": "https:\/\/genrage.com\/products\/nova-black-unisex-straight-fit-baggy-pants",
  "exported_at": "2026-01-02 22:18:18",
  "article": "Men's Gym Wear",
  "timestamp": "2025-05-29 18:58:16",
  "platform": "Genrage"
 },
 {
  "document_id": "LAGbOqOI5Q0To3tC9HhU",
  "product_id": "010GE026",
  "brand": "Genrage",
  "name": "GREY SAIYAN UNISEX STRAIGHT BAGGY PANTS",
  "price": "1699.00",
  "image_urls": "https:\/\/genrage.com\/cdn\/shop\/files\/70_ce25a205-1207-4f90-92a9-1ec913d9f6ca.png?v=1745485088&width=1000",
  "url": "https:\/\/genrage.com\/products\/grey-saiyan-unisex-straight-baggy-pants",
  "exported_at": "2026-01-02 22:18:18",
  "article": "Men's Gym Wear",
  "timestamp": "2025-05-29 18:58:35",
  "platform": "Genrage"
 },
 {
  "document_id": "LBelNZHQRc58wur6rPyH",
  "product_id": "010GE027",
  "brand": "Genrage",
  "name": "Black Nexus Unisex Straight Baggy Pants",
  "price": "1699.00",
  "image_urls": "https:\/\/genrage.com\/cdn\/shop\/files\/black_nexys.png?v=1736340485&width=1000",
  "url": "https:\/\/genrage.com\/products\/black-nexus-unisex-straight-baggy-pants",
  "exported_at": "2026-01-02 22:18:18",
  "article": "Men's Gym Wear",
  "timestamp": "2025-05-29 19:02:09",
  "platform": "Genrage"
 },
 {
  "document_id": "LtkXvE0TX3W5Gz9jXERh",
  "product_id": "010GE028",
  "brand": "Genrage",
  "name": "VEXA UNISEX BOXY VEST",
  "price": "999.00",
  "image_urls": "https:\/\/genrage.com\/cdn\/shop\/files\/vexa_3d.png?v=1735371181&width=1000",
  "url": "https:\/\/genrage.com\/products\/vexa-unisex-boxy-vest",
  "exported_at": "2026-01-02 22:18:18",
  "article": "Men's Gym Wear",
  "timestamp": "2025-05-29 19:09:51",
  "platform": "Genrage"
 },
 {
  "document_id": "MjmamJAC4rerOzwtXOR7",
  "product_id": "010GE029",
  "brand": "Genrage",
  "name": "FALLEN UNISEX BOXY VEST",
  "price": "999.00",
  "image_urls": "https:\/\/genrage.com\/cdn\/shop\/files\/69_1.png?v=1735063735&width=1000",
  "url": "https:\/\/genrage.com\/products\/pishaach-unisex-boxy-vest",
  "exported_at": "2026-01-02 22:18:18",
  "article": "Men's Gym Wear",
  "timestamp": "2025-05-29 19:09:13",
  "platform": "Genrage"
 },
 {
  "document_id": "O7cLQC9VrCWpLJD4B5Y0",
  "product_id": "010GE030",
  "brand": "Genrage",
  "name": "FURIOUS BLACK UNISEX STRAIGHT FIT BAGGY PANTS",
  "price": "1699.00",
  "image_urls": "https:\/\/genrage.com\/cdn\/shop\/files\/82.png?v=1737963514&width=1000",
  "url": "https:\/\/genrage.com\/products\/furious-black-unisex-straight-fit-baggy-pants",
  "exported_at": "2026-01-02 22:18:18",
  "article": "Men's Gym Wear",
  "timestamp": "2025-05-29 18:59:31",
  "platform": "Genrage"
 },
 {
  "document_id": "QU7wZ7UGk12DoTdsrm4N",
  "product_id": "010GE031",
  "brand": "Genrage",
  "name": "SKIN RAUDRA UNISEX STRAIGHT FIT BAGGY PANTS",
  "price": "1699.00",
  "image_urls": "https:\/\/genrage.com\/cdn\/shop\/files\/skin_raidra.png?v=1748152687&width=1000",
  "url": "https:\/\/genrage.com\/products\/skin-raudra-unisex-straight-fit-baggy-pants",
  "exported_at": "2026-01-02 22:18:18",
  "article": "Men's Gym Wear",
  "timestamp": "2025-05-29 18:38:47",
  "platform": "Genrage"
 },
 {
  "document_id": "RCNq9xOzKQKRm71kOPJb",
  "product_id": "010GE032",
  "brand": "Genrage",
  "name": "Saiyan Black Unisex Straight Fit Baggy Pants",
  "price": "1699.00",
  "image_urls": "https:\/\/genrage.com\/cdn\/shop\/files\/1_12.png?v=1736672510&width=1000",
  "url": "https:\/\/genrage.com\/products\/saiyan-black-unisex-straight-fit-baggy-pants",
  "exported_at": "2026-01-02 22:18:18",
  "article": "Men's Gym Wear",
  "timestamp": "2025-05-29 18:56:14",
  "platform": "Genrage"
 },
 {
  "document_id": "SE1ntlsZSKz9HIwCAJwJ",
  "product_id": "010GE033",
  "brand": "Genrage",
  "name": "VISHWA UNISEX BOXY VEST",
  "price": "999.00",
  "image_urls": "https:\/\/genrage.com\/cdn\/shop\/files\/21_5.png?v=1738481058&width=1000",
  "url": "https:\/\/genrage.com\/products\/vishwa-unisex-boxy-vest",
  "exported_at": "2026-01-02 22:18:18",
  "article": "Men's Gym Wear",
  "timestamp": "2025-05-29 19:06:40",
  "platform": "Genrage"
 },
 {
  "document_id": "SqrNQQCFPwW0vOIttVHf",
  "product_id": "010GE034",
  "brand": "Genrage",
  "name": "HEBI UNISEX STRAIGHT FIT BAGGY PANTS",
  "price": "1799.00",
  "image_urls": "https:\/\/genrage.com\/cdn\/shop\/files\/1_9.png?v=1742290653&width=1000",
  "url": "https:\/\/genrage.com\/products\/hebi-unisex-straight-fit-baggy-pants",
  "exported_at": "2026-01-02 22:18:18",
  "article": "Men's Gym Wear",
  "timestamp": "2025-05-29 19:01:04",
  "platform": "Genrage"
 },
 {
  "document_id": "a0002af1-6724-416b-a819-14148cbcfb5b",
  "product_id": "010XM048",
  "brand": "Xtreme X Martial Arts",
  "name": "Nightcore Compression Zipper",
  "price": "1199",
  "image_urls": "https:\/\/xtremexmartialarts.com\/cdn\/shop\/files\/T-SHIRTS-50.jpg?v=1754022183&width=1944",
  "url": "https:\/\/xtremexmartialarts.com\/product\/nightcore-compression-zipper\/?attribute_pa_color=black",
  "material": "Polyester",
  "exported_at": "2026-01-02 22:18:18",
  "article": "Men's Apparel",
  "timestamp": "2025-06-15 19:37:27",
  "category": "Men's Apparel",
  "platform": "Xtreme X Martial Arts"
 },
 {
  "document_id": "ac2c3f2d-5776-47e8-8eb7-2aaf01b6cdda",
  "product_id": "010XM049",
  "brand": "Xtreme X Martial Arts",
  "name": "Immortal Unisex Oversized Tshirt",
  "price": "999",
  "image_urls": "https:\/\/xtremexmartialarts.com\/wp-content\/uploads\/2025\/06\/hr-510x611.jpg, https:\/\/xtremexmartialarts.com\/wp-content\/uploads\/2025\/06\/back-view-hanging-t-shirt-mockup-white-tee-on-vibrant-red-wall-minimalist-display-bold-and-modern-aesthetic1-0994-29-1-510x638.jpg",
  "url": "https:\/\/xtremexmartialarts.com\/product\/immortal-unisex-oversized-tshirt\/",
  "material": "Polyester",
  "exported_at": "2026-01-02 22:18:18",
  "article": "Men's Apparel",
  "timestamp": "2025-06-15 17:53:02",
  "category": "Men's Apparel",
  "platform": "Xtreme X Martial Arts"
 },
 {
  "document_id": "ae954143-8ead-4dcc-ab2c-7c4bbfa0aaa1",
  "product_id": "010XM050",
  "brand": "Xtreme X Martial Arts",
  "name": "ViperX Unisex Oversized Tshirt",
  "price": "899",
  "image_urls": "https:\/\/xtremexmartialarts.com\/wp-content\/uploads\/2025\/02\/minimalist-studio-t-shirt-mockup-floating-display-with-sunlit-effect-and-subtle-textures-596-9-1-510x611.jpg.webp, https:\/\/xtremexmartialarts.com\/wp-content\/uploads\/2025\/02\/folded-white-tshirt-mockup-on-wooden-surface-0390-3-510x408.jpg.webp",
  "url": "https:\/\/xtremexmartialarts.com\/product\/viperx-unisex-oversized-tshirt\/",
  "material": "Polyester",
  "exported_at": "2026-01-02 22:18:18",
  "article": "Men's Apparel",
  "timestamp": "2025-06-15 19:37:27",
  "category": "Men's Apparel",
  "platform": "Xtreme X Martial Arts"
 },
 {
  "document_id": "af903225-1a27-4d74-bcba-9e83f45be7b7",
  "product_id": "010XM051",
  "brand": "Xtreme X Martial Arts",
  "name": "Darksteel Unisex Joggers",
  "price": "1199",
  "image_urls": "https:\/\/xtremexmartialarts.com\/wp-content\/uploads\/2024\/12\/image00034-510x611.png, https:\/\/xtremexmartialarts.com\/wp-content\/uploads\/2024\/12\/image00035-510x510.png, https:\/\/xtremexmartialarts.com\/wp-content\/uploads\/2024\/12\/image00036-510x510.png",
  "url": "https:\/\/xtremexmartialarts.com\/product\/darksteel-unisex-joggers\/",
  "material": "Polyester",
  "exported_at": "2026-01-02 22:18:18",
  "article": "Men's Apparel",
  "timestamp": "2025-06-15 19:37:27",
  "category": "Men's Apparel",
  "platform": "Xtreme X Martial Arts"
 },
 {
  "document_id": "b767925c-0ff4-4a18-82bc-0dbd6721b696",
  "product_id": "010XM052",
  "brand": "Xtreme X Martial Arts",
  "name": "NYC Unisex Jogger",
  "price": "999",
  "image_urls": "https:\/\/xtremexmartialarts.com\/wp-content\/uploads\/2025\/01\/jogger-16-510x611.jpg, https:\/\/xtremexmartialarts.com\/wp-content\/uploads\/2025\/01\/1L9A1099-510x765.jpg, https:\/\/xtremexmartialarts.com\/wp-content\/uploads\/2025\/01\/1L9A1103-510x765.jpg",
  "url": "https:\/\/xtremexmartialarts.com\/product\/nyc-unisex-joggers\/?attribute_pa_color=coffee-brown",
  "material": "Polyester",
  "exported_at": "2026-01-02 22:18:18",
  "article": "Men's Apparel",
  "timestamp": "2025-06-15 19:37:27",
  "category": "Men's Apparel",
  "platform": "Xtreme X Martial Arts"
 },
 {
  "document_id": "b9894a62-08cd-4ae3-a383-fcb77dcae1a3",
  "product_id": "010XM053",
  "brand": "Xtreme X Martial Arts",
  "name": "Snake Flow Unisex Oversized Tshirt",
  "price": "999",
  "image_urls": "https:\/\/xtremexmartialarts.com\/wp-content\/uploads\/2025\/04\/t-1-510x611.jpg, https:\/\/xtremexmartialarts.com\/wp-content\/uploads\/2025\/04\/front-view-hanging-t-shirt-mockup-white-tee-against-deep-red-wall-clean-and-eye-catching-presentation-0995-23-510x638.jpg, https:\/\/xtremexmartialarts.com\/wp-content\/uploads\/2025\/04\/back-view-hanging-t-shirt-mockup-white-tee-on-vibrant-red-wall-minimalist-display-bold-and-modern-aesthetic1-0994-24-510x638.jpg",
  "url": "https:\/\/xtremexmartialarts.com\/product\/snake-flow-unisex-oversized-tshirt\/",
  "material": "Polyester",
  "exported_at": "2026-01-02 22:18:18",
  "article": "Men's Apparel",
  "timestamp": "2025-06-15 18:41:08",
  "category": "Men's Apparel",
  "platform": "Xtreme X Martial Arts"
 },
 {
  "document_id": "bbf04660-748e-4014-a595-2703b5d36b9d",
  "product_id": "010XM054",
  "brand": "Xtreme X Martial Arts",
  "name": "Blacknova Compression Tshirt Half Sleeve",
  "price": "1199",
  "image_urls": "https:\/\/xtremexmartialarts.com\/cdn\/shop\/files\/T-SHIRTS-9.jpg?v=1754023278&width=1944",
  "url": "https:\/\/xtremexmartialarts.com\/product\/blacknova-compression-tshirt-half-sleeve\/?attribute_pa_color=black-blue",
  "material": "Polyester",
  "exported_at": "2026-01-02 22:18:18",
  "article": "Men's Apparel",
  "timestamp": "2025-06-15 19:37:27",
  "category": "Men's Apparel",
  "platform": "Xtreme X Martial Arts"
 },
 {
  "document_id": "bf9552a9-6918-4a87-ad7d-a4ec33d58cde",
  "product_id": "010XM055",
  "brand": "Xtreme X Martial Arts",
  "name": "Falcon Unisex Oversized Hoodie",
  "price": "1599",
  "image_urls": "https:\/\/xtremexmartialarts.com\/wp-content\/uploads\/2024\/11\/hoodie-4-510x611.jpg, https:\/\/xtremexmartialarts.com\/wp-content\/uploads\/2024\/11\/1L9A3117-scaled-510x765.jpg, https:\/\/xtremexmartialarts.com\/wp-content\/uploads\/2024\/11\/1L9A3119-scaled-510x765.jpg.webp",
  "url": "https:\/\/xtremexmartialarts.com\/product\/falcon-unisex-oversized-hoodie-2\/",
  "material": "Polyester",
  "exported_at": "2026-01-02 22:18:18",
  "article": "Men's Apparel",
  "timestamp": "2025-06-15 19:37:27",
  "category": "Men's Apparel",
  "platform": "Xtreme X Martial Arts"
 },
 {
  "document_id": "c649cd74-35e2-4d99-b069-e915b9c164fa",
  "product_id": "010XM056",
  "brand": "Xtreme X Martial Arts",
  "name": "Alpha Compression Tshirt Half Sleeve",
  "price": "1199",
  "image_urls": "https:\/\/xtremexmartialarts.com\/wp-content\/uploads\/2025\/04\/image000101-1-Photoroom.png",
  "url": "https:\/\/xtremexmartialarts.com\/product\/alpha-compression-tshirt-half-sleeve\/?attribute_pa_color=apple-green",
  "material": "Polyester",
  "exported_at": "2026-01-02 22:18:18",
  "article": "Men's Apparel",
  "timestamp": "2025-06-15 19:37:27",
  "category": "Men's Apparel",
  "platform": "Xtreme X Martial Arts"
 },
 {
  "document_id": "c66d16d9-89e7-4890-96c7-b1e121679732",
  "product_id": "010XM057",
  "brand": "Xtreme X Martial Arts",
  "name": "Speedcore Unisex Joggers",
  "price": "1199",
  "image_urls": "https:\/\/xtremexmartialarts.com\/wp-content\/uploads\/2025\/04\/JOGGER-5-510x611.jpg, https:\/\/xtremexmartialarts.com\/wp-content\/uploads\/2025\/04\/xtremex_03_20-510x765.jpg, https:\/\/xtremexmartialarts.com\/wp-content\/uploads\/2025\/04\/xtremex_03_18-510x765.jpg",
  "url": "https:\/\/xtremexmartialarts.com\/product\/speedcore-unisex-joggers\/",
  "material": "Polyester",
  "exported_at": "2026-01-02 22:18:18",
  "article": "Men's Apparel",
  "timestamp": "2025-06-15 19:37:27",
  "category": "Men's Apparel",
  "platform": "Xtreme X Martial Arts"
 },
 {
  "document_id": "c8d22bc2-3823-4aaa-9775-6cc6e8882a17",
  "product_id": "010XM058",
  "brand": "Xtreme X Martial Arts",
  "name": "DominatorX Compression Zipper",
  "price": "1199",
  "image_urls": "https:\/\/xtremexmartialarts.com\/cdn\/shop\/files\/T-SHIRTS-45.jpg?v=1754023558&width=1944",
  "url": "https:\/\/xtremexmartialarts.com\/product\/dominatorx-compression-zipper\/",
  "material": "Polyester",
  "exported_at": "2026-01-02 22:18:18",
  "article": "Men's Apparel",
  "timestamp": "2025-06-15 18:41:08",
  "category": "Men's Apparel",
  "platform": "Xtreme X Martial Arts"
 },
 {
  "document_id": "ce54b131-30f5-43f3-b36c-a452cb3af347",
  "product_id": "010XM059",
  "brand": "Xtreme X Martial Arts",
  "name": "Warning Unisex Joggers",
  "price": "999",
  "image_urls": "https:\/\/xtremexmartialarts.com\/wp-content\/uploads\/2025\/02\/jogger-3-510x611.jpg, https:\/\/xtremexmartialarts.com\/wp-content\/uploads\/2025\/02\/1L9A1339-510x765.jpg, https:\/\/xtremexmartialarts.com\/wp-content\/uploads\/2025\/02\/1L9A1324-510x765.jpg",
  "url": "https:\/\/xtremexmartialarts.com\/product\/warning-unisex-joggers\/",
  "material": "Polyester",
  "exported_at": "2026-01-02 22:18:18",
  "article": "Men's Apparel",
  "timestamp": "2025-06-15 19:37:27",
  "category": "Men's Apparel",
  "platform": "Xtreme X Martial Arts"
 },
 {
  "document_id": "ceb43dce-8da4-4d6b-9785-abb80722a5a5",
  "product_id": "010XM060",
  "brand": "Xtreme X Martial Arts",
  "name": "Venomstrike Unisex Joggers",
  "price": "999",
  "image_urls": "https:\/\/xtremexmartialarts.com\/wp-content\/uploads\/2024\/12\/image00019-510x611.png, https:\/\/xtremexmartialarts.com\/wp-content\/uploads\/2024\/12\/image00018-510x510.png, https:\/\/xtremexmartialarts.com\/wp-content\/uploads\/2024\/12\/image00020-510x510.png",
  "url": "https:\/\/xtremexmartialarts.com\/product\/venomstrike-unisex-joggers\/",
  "material": "Polyester",
  "exported_at": "2026-01-02 22:18:18",
  "article": "Men's Apparel",
  "timestamp": "2025-06-15 19:37:27",
  "category": "Men's Apparel",
  "platform": "Xtreme X Martial Arts"
 },
 {
  "document_id": "d3a50fe6-d19c-4d73-aace-b8a06f2d8397",
  "product_id": "010XM061",
  "brand": "Xtreme X Martial Arts",
  "name": "Sacrifice Unisex Oversized Tshirt",
  "price": "999",
  "image_urls": "https:\/\/xtremexmartialarts.com\/wp-content\/uploads\/2025\/04\/SACRIFICE-TSHIRT-510x611.jpg, https:\/\/xtremexmartialarts.com\/wp-content\/uploads\/2025\/04\/front-view-hanging-t-shirt-mockup-white-tee-against-deep-red-wall-clean-and-eye-catching-presentation-0995-13-510x638.jpg",
  "url": "https:\/\/xtremexmartialarts.com\/product\/sacrifice-unisex-oversized-tshirt\/",
  "material": "Polyester",
  "exported_at": "2026-01-02 22:18:18",
  "article": "Men's Apparel",
  "timestamp": "2025-06-15 18:41:08",
  "category": "Men's Apparel",
  "platform": "Xtreme X Martial Arts"
 },
 {
  "document_id": "dWpQtRa0ZWO5q507Ebtm",
  "product_id": "010GE035",
  "brand": "Genrage",
  "name": "BLACK APEX UNISEX BOXY VEST",
  "price": "999.00",
  "image_urls": "https:\/\/genrage.com\/cdn\/shop\/files\/64_850f358b-54ae-4531-b293-d971ee6a2aad.png?v=1744014472&width=1000",
  "url": "https:\/\/genrage.com\/products\/black-apex-unisex-boxy-vest",
  "exported_at": "2026-01-02 22:18:18",
  "article": "Men's Gym Wear",
  "timestamp": "2025-05-29 19:11:07",
  "platform": "Genrage"
 },
 {
  "document_id": "dae30320-9bd8-4a50-80a8-c614d31e1894",
  "product_id": "010XM062",
  "brand": "Xtreme X Martial Arts",
  "name": "Warrior Unisex Oversized Hoodie",
  "price": "1599",
  "image_urls": "https:\/\/xtremexmartialarts.com\/wp-content\/uploads\/2024\/11\/hoodie-3-510x611.jpg, https:\/\/xtremexmartialarts.com\/wp-content\/uploads\/2024\/11\/1L9A3148-scaled-510x765.jpg.webp, https:\/\/xtremexmartialarts.com\/wp-content\/uploads\/2024\/11\/1L9A3146-scaled-510x765.jpg.webp",
  "url": "https:\/\/xtremexmartialarts.com\/product\/warrior-unisex-oversized-hoodie-2\/",
  "material": "Polyester",
  "exported_at": "2026-01-02 22:18:18",
  "article": "Men's Apparel",
  "timestamp": "2025-06-15 19:37:27",
  "category": "Men's Apparel",
  "platform": "Xtreme X Martial Arts"
 },
 {
  "document_id": "df01ae54-d25b-43fa-ab3e-9352eb9f2140",
  "product_id": "010XM063",
  "brand": "Xtreme X Martial Arts",
  "name": "Bolt Unisex Joggers",
  "price": "999",
  "image_urls": "https:\/\/xtremexmartialarts.com\/wp-content\/uploads\/2024\/11\/7.2-1-510x611.png, https:\/\/xtremexmartialarts.com\/wp-content\/uploads\/2024\/11\/1L9A3149-scaled-510x765.jpg, https:\/\/xtremexmartialarts.com\/wp-content\/uploads\/2024\/11\/1L9A3138-scaled-510x765.jpg",
  "url": "https:\/\/xtremexmartialarts.com\/product\/bolt-unisex-joggers\/?attribute_pa_color=sand",
  "material": "Polyester",
  "exported_at": "2026-01-02 22:18:18",
  "article": "Men's Apparel",
  "timestamp": "2025-06-15 19:37:27",
  "category": "Men's Apparel",
  "platform": "Xtreme X Martial Arts"
 },
 {
  "document_id": "df2a01e8-5bda-4ef1-879b-545879d8a33d",
  "product_id": "010XM064",
  "brand": "Xtreme X Martial Arts",
  "name": "Night Web Compression Tshirt Full Sleeve",
  "price": "949",
  "image_urls": "https:\/\/xtremexmartialarts.com\/cdn\/shop\/files\/T-SHIRTS-11_0243665b-3a29-446a-aa45-0c2353f9512b.jpg?v=1754022934&width=1944",
  "url": "https:\/\/xtremexmartialarts.com\/product\/night-web-compression-tshirt-full-sleeve\/",
  "material": "Polyester",
  "exported_at": "2026-01-02 22:18:18",
  "article": "Men's Apparel",
  "timestamp": "2025-06-15 19:37:27",
  "category": "Men's Apparel",
  "platform": "Xtreme X Martial Arts"
 },
 {
  "document_id": "duIpdvan1O7TF7BDzJdF",
  "product_id": "010GE036",
  "brand": "Genrage",
  "name": "YAGNA UNISEX STRAIGHT FIT BAGGY PANTS",
  "price": "1699.00",
  "image_urls": "https:\/\/genrage.com\/cdn\/shop\/files\/12_2.png?v=1734410703&width=1000",
  "url": "https:\/\/genrage.com\/products\/yagna-unisex-straight-fit-baggy-pants",
  "exported_at": "2026-01-02 22:18:18",
  "article": "Men's Gym Wear",
  "timestamp": "2025-05-29 19:03:02",
  "platform": "Genrage"
 },
 {
  "document_id": "e4d8zsVm8IqKnTLfKfGK",
  "product_id": "010GE037",
  "brand": "Genrage",
  "name": "ONYX BLACK COMPRESSION TANK TOP",
  "price": "799.00",
  "image_urls": "https:\/\/genrage.com\/cdn\/shop\/files\/BUNDIBLACK.png?v=1734410913&width=1000",
  "url": "https:\/\/genrage.com\/products\/onyx-black-compression-tank-top",
  "exported_at": "2026-01-02 22:18:18",
  "article": "Men's Gym Wear",
  "timestamp": "2025-05-29 19:07:32",
  "platform": "Genrage"
 },
 {
  "document_id": "e57652ff-f2cc-4fe6-9f74-93bdecab56d2",
  "product_id": "010XM065",
  "brand": "Xtreme X Martial Arts",
  "name": "Blood Drip Unisex Joggers",
  "price": "999",
  "image_urls": "https:\/\/xtremexmartialarts.com\/wp-content\/uploads\/2025\/02\/new-jogger-5-510x611.jpg, https:\/\/xtremexmartialarts.com\/wp-content\/uploads\/2025\/02\/1L9A1362-510x765.jpg, https:\/\/xtremexmartialarts.com\/wp-content\/uploads\/2025\/02\/1L9A1367-510x765.jpg",
  "url": "https:\/\/xtremexmartialarts.com\/product\/blood-drip-unisex-joggers\/",
  "material": "Polyester",
  "exported_at": "2026-01-02 22:18:18",
  "article": "Men's Apparel",
  "timestamp": "2025-06-15 19:37:27",
  "category": "Men's Apparel",
  "platform": "Xtreme X Martial Arts"
 },
 {
  "document_id": "e86725ba-c058-4ff7-ba8a-9d6833d57afc",
  "product_id": "010XM066",
  "brand": "Xtreme X Martial Arts",
  "name": "Rage Unisex Joggers",
  "price": "999",
  "image_urls": "https:\/\/xtremexmartialarts.com\/wp-content\/uploads\/2024\/12\/image00007-510x611.png, https:\/\/xtremexmartialarts.com\/wp-content\/uploads\/2024\/12\/image00008-510x510.png, https:\/\/xtremexmartialarts.com\/wp-content\/uploads\/2024\/12\/image00009-510x510.png",
  "url": "https:\/\/xtremexmartialarts.com\/product\/rage-unisex-joggers\/",
  "material": "Polyester",
  "exported_at": "2026-01-02 22:18:18",
  "article": "Men's Apparel",
  "timestamp": "2025-06-15 19:37:27",
  "category": "Men's Apparel",
  "platform": "Xtreme X Martial Arts"
 },
 {
  "document_id": "eB0fVWUPwxjLtNEfA416",
  "product_id": "010GE038",
  "brand": "Genrage",
  "name": "Onsu Unisex Straight Fit Baggy Pants",
  "price": "1699.00",
  "image_urls": "https:\/\/genrage.com\/cdn\/shop\/files\/3_PNG.png?v=1734410670&width=1000",
  "url": "https:\/\/genrage.com\/products\/onsu-unisex-straight-fit-baggy-pants",
  "exported_at": "2026-01-02 22:18:18",
  "article": "Men's Gym Wear",
  "timestamp": "2025-05-29 19:03:44",
  "platform": "Genrage"
 },
 {
  "document_id": "eCZdrirXPolMg4DfemuA",
  "product_id": "010GE039",
  "brand": "Genrage",
  "name": "DRACON UNISEX STRAIGHT FIT BAGGY PANTS",
  "price": "1799.00",
  "image_urls": "https:\/\/genrage.com\/cdn\/shop\/files\/1_PNG_1.png?v=1734410676&width=1000",
  "url": "https:\/\/genrage.com\/products\/dracon-unisex-straight-fit-baggy-pants",
  "exported_at": "2026-01-02 22:18:18",
  "article": "Men's Gym Wear",
  "timestamp": "2025-05-29 19:03:18",
  "platform": "Genrage"
 },
 {
  "document_id": "f85247ce-8008-46c2-b157-287749e7bc0d",
  "product_id": "010XM067",
  "brand": "Xtreme X Martial Arts",
  "name": "Super Suit Compression Tshirt Half Sleeve",
  "price": "899",
  "image_urls": "https:\/\/xtremexmartialarts.com\/cdn\/shop\/files\/T-SHIRTS-20.jpg?v=1754023163&width=1944",
  "url": "https:\/\/xtremexmartialarts.com\/product\/super-suit-compression-tshirt-half-sleeve\/",
  "material": "Polyester",
  "exported_at": "2026-01-02 22:18:18",
  "article": "Men's Apparel",
  "timestamp": "2025-06-15 19:37:27",
  "category": "Men's Apparel",
  "platform": "Xtreme X Martial Arts"
 },
 {
  "document_id": "fCiUo0a8Rg2NPIlK7b6F",
  "product_id": "010GE040",
  "brand": "Genrage",
  "name": "PYTHONIC UNISEX STRAIGHT FIT BAGGY PANTS",
  "price": "1699.00",
  "image_urls": "https:\/\/genrage.com\/cdn\/shop\/files\/AZDVDZS_8d8480da-2a4b-43e4-b0bc-18d5fb06ea47.png?v=1742290588&width=1000",
  "url": "https:\/\/genrage.com\/products\/pythonic-unisex-straight-fit-baggy-pants?pr_prod_strat=e5_desc&pr_rec_id=661515208&pr_rec_pid=8183987798254&pr_ref_pid=8803801956590&pr_seq=uniform",
  "exported_at": "2026-01-02 22:18:18",
  "article": "Men's Gym Wear",
  "timestamp": "2025-05-29 18:20:58",
  "platform": "Genrage"
 },
 {
  "document_id": "ff660fcb-2525-4e75-accf-82990a63c76a",
  "product_id": "010XM068",
  "brand": "Xtreme X Martial Arts",
  "name": "Drift Unisex Joggers",
  "price": "999",
  "image_urls": "https:\/\/xtremexmartialarts.com\/wp-content\/uploads\/2025\/02\/new-jogger-4-510x611.jpg, https:\/\/xtremexmartialarts.com\/wp-content\/uploads\/2025\/02\/1L9A1351-510x765.jpg, https:\/\/xtremexmartialarts.com\/wp-content\/uploads\/2025\/02\/1L9A1352-510x765.jpg",
  "url": "https:\/\/xtremexmartialarts.com\/product\/drift-unisex-joggers\/",
  "material": "Polyester",
  "exported_at": "2026-01-02 22:18:18",
  "article": "Men's Apparel",
  "timestamp": "2025-06-15 19:37:27",
  "category": "Men's Apparel",
  "platform": "Xtreme X Martial Arts"
 },
 {
  "document_id": "gBj3Ojl1WrzUt0AxlBxv",
  "product_id": "010GE041",
  "brand": "Genrage",
  "name": "SHADOW UNISEX BOXY VEST",
  "price": "999.00",
  "image_urls": "https:\/\/genrage.com\/cdn\/shop\/files\/37_7a03ad79-76c7-4d48-b7b9-97b9c6550cdb.png?v=1744223901&width=1000",
  "url": "https:\/\/genrage.com\/products\/shadow-unisex-boxy-vest",
  "exported_at": "2026-01-02 22:18:18",
  "article": "Men's Gym Wear",
  "timestamp": "2025-05-29 19:06:56",
  "platform": "Genrage"
 },
 {
  "document_id": "huKgFzLVv9H36zTgxSkJ",
  "product_id": "010GE042",
  "brand": "Genrage",
  "name": "MAXUS BLACK UNISEX STRAIGHT FIT BAGGY PANTS",
  "price": "1699.00",
  "image_urls": "https:\/\/genrage.com\/cdn\/shop\/files\/9_4.png?v=1737633879&width=1000",
  "url": "https:\/\/genrage.com\/products\/maxus-black-unisex-straight-fit-baggy-pants",
  "exported_at": "2026-01-02 22:18:18",
  "article": "Men's Gym Wear",
  "timestamp": "2025-05-29 18:57:25",
  "platform": "Genrage"
 },
 {
  "document_id": "jmNSwJkKxHX2ZIp9FAT1",
  "product_id": "010GE043",
  "brand": "Genrage",
  "name": "1,699.00",
  "price": "1699.00",
  "image_urls": "https:\/\/genrage.com\/cdn\/shop\/files\/AZDVDZS_8d8480da-2a4b-43e4-b0bc-18d5fb06ea47.png?v=1742290588&width=1000",
  "url": "https:\/\/genrage.com\/products\/pythonic-unisex-straight-fit-baggy-pants",
  "exported_at": "2026-01-02 22:18:18",
  "article": "Men's Gym Wear",
  "timestamp": "2025-05-29 18:39:34",
  "platform": "Genrage"
 },
 {
  "document_id": "l605awIqqny45GdqGHKr",
  "product_id": "010GE044",
  "brand": "Genrage",
  "name": "BLACK NEXUS UNISEX STRAIGHT BAGGY PANTS",
  "price": "1699.00",
  "image_urls": "https:\/\/genrage.com\/cdn\/shop\/files\/black_nexys.png?v=1736340485&width=1000",
  "url": "https:\/\/genrage.com\/products\/black-nexus-unisex-straight-baggy-pants",
  "exported_at": "2026-01-02 22:18:18",
  "article": "Men's Gym Wear",
  "timestamp": "2025-05-29 19:01:21",
  "platform": "Genrage"
 },
 {
  "document_id": "n8AcJ17hmB0wu6EiSlo7",
  "product_id": "010GE045",
  "brand": "Genrage",
  "name": "TOJI UNISEX STRAIGHT FIT BAGGY PANTS",
  "price": "1699.00",
  "image_urls": "https:\/\/genrage.com\/cdn\/shop\/files\/38_1.png?v=1743699725&width=1000",
  "url": "https:\/\/genrage.com\/products\/toji-unisex-straight-fit-baggy-pants",
  "exported_at": "2026-01-02 22:18:18",
  "article": "Men's Gym Wear",
  "timestamp": "2025-05-29 18:16:01",
  "platform": "Genrage"
 },
 {
  "document_id": "oILgaYmXPGkeYquihXpM",
  "product_id": "010GE046",
  "brand": "Genrage",
  "name": "THRONE BLACK UNISEX STRAIGHT FIT BAGGY PANTS",
  "price": "1699.00",
  "image_urls": "https:\/\/genrage.com\/cdn\/shop\/files\/throne.png?v=1734410880&width=1000",
  "url": "https:\/\/genrage.com\/products\/throne-black-unisex-straight-fit-baggy-pants",
  "exported_at": "2026-01-02 22:18:18",
  "article": "Men's Gym Wear",
  "timestamp": "2025-05-29 19:02:45",
  "platform": "Genrage"
 },
 {
  "document_id": "oPI99hplmUHljMNV87Nc",
  "product_id": "010GE047",
  "brand": "Genrage",
  "name": "SAMUDRA UNISEX BOXY VEST",
  "price": "999.00",
  "image_urls": "https:\/\/genrage.com\/cdn\/shop\/files\/24f.png?v=1746884503&width=1000",
  "url": "https:\/\/genrage.com\/products\/samudra-unisex-boxy-vest",
  "exported_at": "2026-01-02 22:18:18",
  "article": "Men's Gym Wear",
  "timestamp": "2025-05-29 19:08:02",
  "platform": "Genrage"
 },
 {
  "document_id": "ohw8TvUhkKNSRBC8JSqR",
  "product_id": "010GE048",
  "brand": "Genrage",
  "name": "SHIRO UNISEX GREY STRAIGHT FIT BAGGY PANTS",
  "price": "1699.0",
  "image_urls": "https:\/\/genrage.com\/cdn\/shop\/files\/76.png?v=1745847406&width=1000",
  "url": "https:\/\/genrage.com\/products\/shiro-unisex-grey-straight-fit-baggy-pants",
  "exported_at": "2026-01-02 22:18:18",
  "article": "Men's Gym Wear",
  "timestamp": "2025-05-29 18:56:32",
  "platform": "Genrage"
 },
 {
  "document_id": "pJlR6N3ChX8VmF7crsTY",
  "product_id": "010GE049",
  "brand": "Genrage",
  "name": "TANTRA UNISEX PLUM BOXY VEST",
  "price": "999.00",
  "image_urls": "https:\/\/genrage.com\/cdn\/shop\/files\/3_4.png?v=1734410724&width=1000",
  "url": "https:\/\/genrage.com\/products\/tantra-unisex-black-boxy-vest",
  "exported_at": "2026-01-02 22:18:18",
  "article": "Men's Gym Wear",
  "timestamp": "2025-05-29 19:05:49",
  "platform": "Genrage"
 },
 {
  "document_id": "pqJv3S1jeaEsV2O2eXAk",
  "product_id": "010GE050",
  "brand": "Genrage",
  "name": "Toji Unisex Straight Fit Baggy Pants",
  "price": "1699.00",
  "image_urls": "https:\/\/genrage.com\/cdn\/shop\/files\/38_1.png?v=1743699725&width=1000",
  "url": "https:\/\/genrage.com\/products\/toji-unisex-straight-fit-baggy-pants",
  "exported_at": "2026-01-02 22:18:18",
  "article": "Men's Gym Wear",
  "timestamp": "2025-05-29 18:28:33",
  "platform": "Genrage"
 },
 {
  "document_id": "qooSYwdruehp2X3SRcc6",
  "product_id": "010GE051",
  "brand": "Genrage",
  "name": "GREY MUTATION UNISEX STRAIGHT FIT BAGGY PANTS",
  "price": "1799.00",
  "image_urls": "https:\/\/genrage.com\/cdn\/shop\/files\/68_323f64ed-42b6-4539-9dcc-db9873a73cd2.png?v=1745484981&width=1000",
  "url": "https:\/\/genrage.com\/products\/grey-mutation-unisex-straight-fit-baggy-pants",
  "exported_at": "2026-01-02 22:18:18",
  "article": "Men's Gym Wear",
  "timestamp": "2025-05-29 18:58:00",
  "platform": "Genrage"
 },
 {
  "document_id": "rjN3KeBvrYbe5GmYEPKx",
  "product_id": "010GE052",
  "brand": "Genrage",
  "name": "HAUNT UNISEX GREY STRAIGHT FIT BAGGY PANTS",
  "price": "1699.00",
  "image_urls": "https:\/\/genrage.com\/cdn\/shop\/files\/83.png?v=1747046415&width=1000",
  "url": "https:\/\/genrage.com\/products\/haunt-unisex-grey-straight-fit-baggy-pants",
  "exported_at": "2026-01-02 22:18:18",
  "article": "Men's Gym Wear",
  "timestamp": "2025-05-29 19:04:42",
  "platform": "Genrage"
 },
 {
  "document_id": "tE7O3XXAVP4QIR4Fp2QV",
  "product_id": "010GE053",
  "brand": "Genrage",
  "name": "BRUTAL BROWN UNISEX BOXY VEST",
  "price": "999.00",
  "image_urls": "https:\/\/genrage.com\/cdn\/shop\/files\/49.png?v=1743257956&width=1000",
  "url": "https:\/\/genrage.com\/products\/brutal-chocolate-brown-unisex-boxy-vest",
  "exported_at": "2026-01-02 22:18:18",
  "article": "Men's Gym Wear",
  "timestamp": "2025-05-29 19:10:47",
  "platform": "Genrage"
 },
 {
  "document_id": "tRQwzhgYbTs8lOmW8qIn",
  "product_id": "010GE054",
  "brand": "Genrage",
  "name": "DUSK GREY UNISEX BOXY VEST",
  "price": "999.00",
  "image_urls": "https:\/\/genrage.com\/cdn\/shop\/files\/28f_1.png?v=1747849095&width=1000",
  "url": "https:\/\/genrage.com\/products\/dusk-grey-unisex-boxy-vest",
  "exported_at": "2026-01-02 22:18:18",
  "article": "Men's Gym Wear",
  "timestamp": "2025-05-29 19:11:25",
  "platform": "Genrage"
 },
 {
  "document_id": "vYn01wjXXYV5eGgCQCnG",
  "product_id": "010GE055",
  "brand": "Genrage",
  "name": "HEAT UNISEX STRAIGHT FIT BAGGY PANTS",
  "price": "1699.00",
  "image_urls": "https:\/\/genrage.com\/cdn\/shop\/files\/ufhyjfc.png?v=1734410655&width=1000",
  "url": "https:\/\/genrage.com\/products\/heat-unisex-straight-fit-baggy-pants?pr_prod_strat=e5_desc&pr_rec_id=4ad5a846f&pr_rec_pid=8604161900782&pr_ref_pid=8183987798254&pr_seq=uniform",
  "exported_at": "2026-01-02 22:18:18",
  "article": "Men's Gym Wear",
  "timestamp": "2025-05-29 18:21:20",
  "platform": "Genrage"
 },
 {
  "document_id": "wT5zjTK9T5fNxdB1SJrv",
  "product_id": "010GE056",
  "brand": "Genrage",
  "name": "LATTE BEIGE SCAR UNISEX BAGGY PANTS",
  "price": "1699.00",
  "image_urls": "https:\/\/genrage.com\/cdn\/shop\/files\/72_53f73480-8433-4148-85d7-09682e19f373.png?v=1744986751&width=1000",
  "url": "https:\/\/genrage.com\/products\/latte-beige-scar-unisex-baggy-pants",
  "exported_at": "2026-01-02 22:18:18",
  "article": "Men's Gym Wear",
  "timestamp": "2025-05-29 18:38:26",
  "platform": "Genrage"
 },
 {
  "document_id": "x85T2QjLmagutq4z3OZX",
  "product_id": "010GE057",
  "brand": "Genrage",
  "name": "MARIA UNISEX BLACK BOXY VEST",
  "price": "999.00",
  "image_urls": "https:\/\/genrage.com\/cdn\/shop\/files\/MARIA1.png?v=1734410813&width=1000",
  "url": "https:\/\/genrage.com\/products\/maria-unisex-black-boxy-vest",
  "exported_at": "2026-01-02 22:18:18",
  "article": "Men's Gym Wear",
  "timestamp": "2025-05-29 19:06:22",
  "platform": "Genrage"
 },
 {
  "document_id": "y59X14EfIyMhhhDQQMv5",
  "product_id": "010GE058",
  "brand": "Genrage",
  "name": "REDEMPTION UNISEX STRAIGHT FIT BAGGY PANTS",
  "price": "1749.00",
  "image_urls": "https:\/\/genrage.com\/cdn\/shop\/files\/10_0b83d07a-6bda-4a31-9270-d2dcb42ac79d.png?v=1739876434&width=1000",
  "url": "https:\/\/genrage.com\/products\/redemption-unisex-straight-fit-baggy-pants",
  "exported_at": "2026-01-02 22:18:18",
  "article": "Men's Gym Wear",
  "timestamp": "2025-05-29 18:56:48",
  "platform": "Genrage"
 },
 {
  "document_id": "yCcTqzwbEFNdm1DEAcfE",
  "product_id": "010GE059",
  "brand": "Genrage",
  "name": "RUTHLESS DARK GREY UNISEX BOXY VEST",
  "price": "999.00",
  "image_urls": "https:\/\/genrage.com\/cdn\/shop\/files\/24_1_75eecd88-f6b0-4c1f-b158-76c51634bb8e.png?v=1744954459&width=1000",
  "url": "https:\/\/genrage.com\/products\/ruthless-light-grey-unisex-boxy-vest",
  "exported_at": "2026-01-02 22:18:18",
  "article": "Men's Gym Wear",
  "timestamp": "2025-05-29 19:07:49",
  "platform": "Genrage"
 },
 {
  "document_id": "ygvHi5gC77HlXDNDlLh2",
  "product_id": "010GE060",
  "brand": "Genrage",
  "name": "BLACK SCAR UNISEX STRAIGHT BAGGY PANTS",
  "price": "1699.00",
  "image_urls": "https:\/\/genrage.com\/cdn\/shop\/files\/9_3.png?v=1734411010&width=1000",
  "url": "https:\/\/genrage.com\/products\/black-scar-unisex-straight-baggy-pants",
  "exported_at": "2026-01-02 22:18:18",
  "article": "Men's Gym Wear",
  "timestamp": "2025-05-29 18:58:53",
  "platform": "Genrage"
 }
]